{"stores": [{"name": "広州Greco", "address": "北海道函館市本町4-19", "budget": "平均予算 4,000 ～ 5,000円", "reward": "飲食金額の50%（最大6,000P）", "url": "https://pc.moppy.jp/fukumoni/item_transfer.php?item_url=https://www.fancrew.jp/detail2-oem/2504823?classicFlg=false", "lat": 41.787933, "lng": 140.751129}, {"name": "まほろば 掛川駅前店", "address": "静岡県掛川市駅前3-3 加藤ビル 1F", "budget": "平均予算 3,000 ～ 4,000円", "reward": "飲食金額の50%（最大5,000P）", "url": "https://pc.moppy.jp/fukumoni/item_transfer.php?item_url=https://www.fancrew.jp/detail2-oem/2503627?classicFlg=false", "lat": 34.771267, "lng": 138.014862}, {"name": "鉄ぱん屋 弁兵衛 広島駅北口店", "address": "広島県広島市東区若草町12-1アクティブインターシティ広島1F", "budget": "平均予算 3,000 ～ 4,000円", "reward": "飲食金額の50%（最大5,500P）", "url": "https://pc.moppy.jp/fukumoni/item_transfer.php?item_url=https://www.fancrew.jp/detail2-oem/2501383?classicFlg=false", "lat": 34.397972, "lng": 132.477692}, {"name": "鶴亀八番 姫路店", "address": "兵庫県姫路市駅前町188-1 グランフェスタ 6番街", "budget": "平均予算 2,000 ～ 3,000円", "reward": "飲食金額の50%（最大3,000P）", "url": "https://pc.moppy.jp/fukumoni/item_transfer.php?item_url=https://www.fancrew.jp/detail2-oem/2504610?classicFlg=false", "lat": 34.827621, "lng": 134.690842}, {"name": "PISOLA 彦根ベルロード店", "address": "滋賀県彦根市平田町435-2", "budget": "平均予算 1,000 ～ 2,000円", "reward": "飲食金額の30%（最大5,000P）", "url": "https://pc.moppy.jp/fukumoni/item_transfer.php?item_url=https://www.fancrew.jp/detail2-oem/2507634?classicFlg=false", "lat": 35.259438, "lng": 136.239594}, {"name": "つけ蕎麦 辛流", "address": "栃木県宇都宮市宿郷1-12-9 宿郷カサブランカビル1階", "budget": "平均予算 1,000 ～ 2,000円", "reward": "飲食金額の50%（最大4,000P）", "url": "https://pc.moppy.jp/fukumoni/item_transfer.php?item_url=https://www.fancrew.jp/detail2-oem/2503096?classicFlg=false", "lat": 36.556507, "lng": 139.900299}, {"name": "もみじ庵 豊洲IHI店", "address": "東京都江東区豊洲3-1-1", "budget": "平均予算 3,000 ～ 4,000円", "reward": "飲食金額の50%（最大4,500P）", "url": "https://pc.moppy.jp/fukumoni/item_transfer.php?item_url=https://www.fancrew.jp/detail2-oem/2504661?classicFlg=false", "lat": 35.65921, "lng": 139.792511}, {"name": "炙りや 楽蔵", "address": "千葉県千葉市中央区新町15-13 丸三新町ビル1F", "budget": "平均予算 3,000 ～ 4,000円", "reward": "飲食金額の50%（最大5,000P）", "url": "https://pc.moppy.jp/fukumoni/item_transfer.php?item_url=https://www.fancrew.jp/detail2-oem/2504491?classicFlg=false", "lat": 35.611488, "lng": 140.111801}, {"name": "炉端とおでん 呼炉凪来 姫路店", "address": "兵庫県姫路市駅前町315 ドレミビル 1F", "budget": "平均予算 3,000 ～ 4,000円", "reward": "飲食金額の50%（最大4,000P）", "url": "https://pc.moppy.jp/fukumoni/item_transfer.php?item_url=https://www.fancrew.jp/detail2-oem/2503232?classicFlg=false", "lat": 34.829098, "lng": 134.692093}, {"name": "にんにく焼肉 プルシン 宮古島店", "address": "沖縄県宮古島市平良下里83-3", "budget": "平均予算 4,000 ～ 5,000円", "reward": "飲食金額の50%（最大5,000P）", "url": "https://pc.moppy.jp/fukumoni/item_transfer.php?item_url=https://www.fancrew.jp/detail2-oem/2505960?classicFlg=false", "lat": 24.803795, "lng": 125.278259}, {"name": "にんにく焼肉 プルシン 久茂地店", "address": "沖縄県那覇市久茂地3-9-9 9番地ビル 1F", "budget": "平均予算 4,000 ～ 5,000円", "reward": "飲食金額の50%（最大5,000P）", "url": "https://pc.moppy.jp/fukumoni/item_transfer.php?item_url=https://www.fancrew.jp/detail2-oem/2505961?classicFlg=false", "lat": 26.21468, "lng": 127.681107}, {"name": "肉バル GABUTTO", "address": "大阪府茨木市西中条町1-1 ハタセViビル 1F", "budget": "平均予算 6,000 ～ 7,000円", "reward": "飲食金額の40%（最大5,000P）", "url": "https://pc.moppy.jp/fukumoni/item_transfer.php?item_url=https://www.fancrew.jp/detail2-oem/2504920?classicFlg=false", "lat": 34.814896, "lng": 135.562424}, {"name": "豚のかんぱい家 西葛西店", "address": "東京都江戸川区西葛西6-15-11", "budget": "平均予算 3,000 ～ 4,500円", "reward": "飲食金額の50%（最大4,500P）", "url": "https://pc.moppy.jp/fukumoni/item_transfer.php?item_url=https://www.fancrew.jp/detail2-oem/2502347?classicFlg=false", "lat": 35.664307, "lng": 139.861008}, {"name": "居酒屋革命 酔っ手羽 近鉄四日市店", "address": "三重県四日市市諏訪栄町6-15 旭ビル 1F・2F", "budget": "平均予算 2,000 ～ 3,000円", "reward": "飲食金額の50%（最大6,000P）", "url": "https://pc.moppy.jp/fukumoni/item_transfer.php?item_url=https://www.fancrew.jp/detail2-oem/2505324?classicFlg=false", "lat": 34.967411, "lng": 136.620056}, {"name": "雪月風花 北野坂", "address": "兵庫県神戸市中央区中山手通1-9-24 エムズ北野坂 1F", "budget": "平均予算 5,000 ～ 6,000円", "reward": "飲食金額の50%（最大5,000P）", "url": "https://pc.moppy.jp/fukumoni/item_transfer.php?item_url=https://www.fancrew.jp/detail2-oem/2504624?classicFlg=false", "lat": 34.695686, "lng": 135.192444}, {"name": "PISOLA 岩出店", "address": "和歌山県岩出市中迫173", "budget": "平均予算 1,000 ～ 2,000円", "reward": "飲食金額の30%（最大5,000P）", "url": "https://pc.moppy.jp/fukumoni/item_transfer.php?item_url=https://www.fancrew.jp/detail2-oem/2500451?classicFlg=false", "lat": 34.261745, "lng": 135.313599}, {"name": "亀山ホルモン", "address": "栃木県小山市駅東通り1-5-13 1F", "budget": "平均予算 4,000 ～ 5,000円", "reward": "飲食金額の50%（最大8,000P）", "url": "https://pc.moppy.jp/fukumoni/item_transfer.php?item_url=https://www.fancrew.jp/detail2-oem/2505966?classicFlg=false", "lat": 36.310356, "lng": 139.807053}, {"name": "一枚焼肉・ソーセージ にくひろ", "address": "兵庫県神戸市中央区北長狭通1-6-11 西阪ビルB1F", "budget": "平均予算 3,000 ～ 4,000円", "reward": "飲食金額の50%（最大5,000P）", "url": "https://pc.moppy.jp/fukumoni/item_transfer.php?item_url=https://www.fancrew.jp/detail2-oem/2501812?classicFlg=false", "lat": 34.69342, "lng": 135.192154}, {"name": "PISOLA 熊谷月見町店", "address": "埼玉県熊谷市月見町2丁目1-65", "budget": "平均予算 1,000 ～ 2,000円", "reward": "飲食金額の30%（最大5,000P）", "url": "https://pc.moppy.jp/fukumoni/item_transfer.php?item_url=https://www.fancrew.jp/detail2-oem/2504592?classicFlg=false", "lat": 36.146332, "lng": 139.36969}, {"name": "PISOLA 甚目寺店", "address": "愛知県あま市下萱津平島16", "budget": "平均予算 1,000 ～ 2,000円", "reward": "飲食金額の30%（最大5,000P）", "url": "https://pc.moppy.jp/fukumoni/item_transfer.php?item_url=https://www.fancrew.jp/detail2-oem/2506933?classicFlg=false", "lat": 35.183624, "lng": 136.835632}, {"name": "PISOLA 宝塚東洋店", "address": "兵庫県宝塚市東洋町5-3", "budget": "平均予算 1,000 ～ 2,000円", "reward": "飲食金額の30%（最大5,000P）", "url": "https://pc.moppy.jp/fukumoni/item_transfer.php?item_url=https://www.fancrew.jp/detail2-oem/2502990?classicFlg=false", "lat": 34.797173, "lng": 135.363632}, {"name": "サンジュウニ", "address": "愛知県春日井市松新町1-23 エクセレント勝川 1F", "budget": "平均予算 4,000 ～ 5,000円", "reward": "飲食金額の50%（最大5,000P）", "url": "https://pc.moppy.jp/fukumoni/item_transfer.php?item_url=https://www.fancrew.jp/detail2-oem/2508784?classicFlg=false", "lat": 35.230984, "lng": 136.95723}, {"name": "オリオン餃子 長岡大手通店", "address": "新潟県長岡市大手通1-4-14", "budget": "平均予算 2,000 ～ 3,000円", "reward": "飲食金額の50%（最大4,000P）", "url": "https://pc.moppy.jp/fukumoni/item_transfer.php?item_url=https://www.fancrew.jp/detail2-oem/2503285?classicFlg=false", "lat": 37.446819, "lng": 138.851379}, {"name": "炭火焼鳥とさか 清水駅前店", "address": "静岡県静岡市清水区真砂町2-32 真砂町第一ビル2", "budget": "平均予算 3,000 ～ 4,000円", "reward": "飲食金額の50%（最大5,000P）", "url": "https://pc.moppy.jp/fukumoni/item_transfer.php?item_url=https://www.fancrew.jp/detail2-oem/2504706?classicFlg=false", "lat": 35.023232, "lng": 138.488083}, {"name": "食悦堂", "address": "大阪府大阪市阿倍野区昭和町5-10-27", "budget": "平均予算 3,000 ～ 4,000円", "reward": "飲食金額の50%（最大4,000P）", "url": "https://pc.moppy.jp/fukumoni/item_transfer.php?item_url=https://www.fancrew.jp/detail2-oem/2502831?classicFlg=false", "lat": 34.622501, "lng": 135.515457}, {"name": "PISOLA 和歌山向店", "address": "和歌山県和歌山市向206-1", "budget": "平均予算 1,000 ～ 2,000円", "reward": "飲食金額の30%（最大5,000P）", "url": "https://pc.moppy.jp/fukumoni/item_transfer.php?item_url=https://www.fancrew.jp/detail2-oem/2500457?classicFlg=false", "lat": 34.255646, "lng": 135.144196}, {"name": "BABY FACE PLANET'S 宇治大久保店", "address": "京都府宇治市大久保町井ノ尻52-1", "budget": "平均予算 2,000 ～ 3,000円", "reward": "飲食金額の30%（最大5,000P）", "url": "https://pc.moppy.jp/fukumoni/item_transfer.php?item_url=https://www.fancrew.jp/detail2-oem/2500406?classicFlg=false", "lat": 34.873112, "lng": 135.770432}, {"name": "PISOLA 鈴鹿中央通店", "address": "三重県鈴鹿市三日市町993-2", "budget": "平均予算 1,000 ～ 2,000円", "reward": "飲食金額の30%（最大5,000P）", "url": "https://pc.moppy.jp/fukumoni/item_transfer.php?item_url=https://www.fancrew.jp/detail2-oem/2500403?classicFlg=false", "lat": 34.875809, "lng": 136.56073}, {"name": "PISOLA 四日市ときわ店", "address": "三重県四日市市ときわ2丁目12-27", "budget": "平均予算 1,000 ～ 2,000円", "reward": "飲食金額の30%（最大5,000P）", "url": "https://pc.moppy.jp/fukumoni/item_transfer.php?item_url=https://www.fancrew.jp/detail2-oem/2500409?classicFlg=false", "lat": 34.967491, "lng": 136.59465}, {"name": "満マル 長居店", "address": "大阪府大阪市住吉区長居東4-3-56", "budget": "平均予算 2,000 ～ 3,000円", "reward": "飲食金額の40%（最大10,000P）", "url": "https://pc.moppy.jp/fukumoni/item_transfer.php?item_url=https://www.fancrew.jp/detail2-oem/2505975?classicFlg=false", "lat": 34.611443, "lng": 135.512939}, {"name": "ステーキハウス88 石垣島店", "address": "沖縄県石垣市新川2373-14", "budget": "平均予算 2,000 ～ 3,000円", "reward": "飲食金額の60%（最大1,000P）", "url": "https://pc.moppy.jp/fukumoni/item_transfer.php?item_url=https://www.fancrew.jp/detail2-oem/2507413?classicFlg=false", "lat": 24.372059, "lng": 124.115646}, {"name": "かんぱい家 西葛西本店", "address": "東京都江戸川区西葛西3-13-2", "budget": "平均予算 3,000 ～ 4,500円", "reward": "飲食金額の50%（最大4,500P）", "url": "https://pc.moppy.jp/fukumoni/item_transfer.php?item_url=https://www.fancrew.jp/detail2-oem/2502345?classicFlg=false", "lat": 35.665871, "lng": 139.856812}, {"name": "炉端とおでん 呼炉凪来 宇都宮店", "address": "栃木県宇都宮市江野町8-12 とらや第二ビル 2F", "budget": "平均予算 2,000 ～ 3,000円", "reward": "飲食金額の50%（最大4,000P）", "url": "https://pc.moppy.jp/fukumoni/item_transfer.php?item_url=https://www.fancrew.jp/detail2-oem/2503863?classicFlg=false", "lat": 36.560215, "lng": 139.882095}, {"name": "スミビトケムリ 宇都宮店", "address": "栃木県宇都宮市江野町8-12 とらや第二ビル 1F", "budget": "平均予算 3,000 ～ 4,000円", "reward": "飲食金額の50%（最大4,000P）", "url": "https://pc.moppy.jp/fukumoni/item_transfer.php?item_url=https://www.fancrew.jp/detail2-oem/2503864?classicFlg=false", "lat": 36.560215, "lng": 139.882095}, {"name": "炉端とおでん 呼炉凪来 成田店", "address": "千葉県成田市花崎町533-10 プレドラガールNARITA 1F", "budget": "平均予算 3,000 ～ 4,000円", "reward": "飲食金額の50%（最大4,000P）", "url": "https://pc.moppy.jp/fukumoni/item_transfer.php?item_url=https://www.fancrew.jp/detail2-oem/2504639?classicFlg=false", "lat": 35.777859, "lng": 140.315765}, {"name": "ステーキハウス88Jr. イオン那覇店", "address": "沖縄県那覇市金城5-10-2 イオン那覇店 3F", "budget": "平均予算 2,000 ～ 3,000円", "reward": "飲食金額の40%（最大1,000P）", "url": "https://pc.moppy.jp/fukumoni/item_transfer.php?item_url=https://www.fancrew.jp/detail2-oem/2507401?classicFlg=false", "lat": 26.196909, "lng": 127.665909}, {"name": "鉄ぱん屋 弁兵衛 横川店", "address": "広島県広島市西区横川町2-9-10", "budget": "平均予算 3,000 ～ 4,000円", "reward": "飲食金額の50%（最大5,500P）", "url": "https://pc.moppy.jp/fukumoni/item_transfer.php?item_url=https://www.fancrew.jp/detail2-oem/2501384?classicFlg=false", "lat": 34.407711, "lng": 132.449799}, {"name": "肉＆ワインBAL COBY 宜野湾店", "address": "沖縄県宜野湾市伊佐2-20-15", "budget": "平均予算 3,000 ～ 4,000円", "reward": "飲食金額の50%（最大5,000P）", "url": "https://pc.moppy.jp/fukumoni/item_transfer.php?item_url=https://www.fancrew.jp/detail2-oem/2501135?classicFlg=false", "lat": 26.287901, "lng": 127.752899}, {"name": "肉匠 晃苑", "address": "青森県八戸市六日町22-2 男山ビル1F", "budget": "平均予算 8,000 ～ 10,000円", "reward": "飲食金額の50%（最大10,000P）", "url": "https://pc.moppy.jp/fukumoni/item_transfer.php?item_url=https://www.fancrew.jp/detail2-oem/2502460?classicFlg=false", "lat": 40.509029, "lng": 141.491989}, {"name": "伊達のくら 仙台東口店", "address": "宮城県仙台市宮城野区榴岡2-3-16", "budget": "平均予算 4,000 ～ 5,000円", "reward": "飲食金額の50%（最大5,000P）", "url": "https://pc.moppy.jp/fukumoni/item_transfer.php?item_url=https://www.fancrew.jp/detail2-oem/2504499?classicFlg=false", "lat": 38.261814, "lng": 140.885223}, {"name": "やきとんひなた とうきょうスカイツリー駅店", "address": "東京都墨田区押上2-1-1", "budget": "平均予算 2,000 ～ 3,000円", "reward": "飲食金額の40%（最大4,000P）", "url": "https://pc.moppy.jp/fukumoni/item_transfer.php?item_url=https://www.fancrew.jp/detail2-oem/2506308?classicFlg=false", "lat": 35.710854, "lng": 139.808777}, {"name": "タイ屋台 999 池袋東口店", "address": "東京都豊島区東池袋1-39-15", "budget": "平均予算 4,000 ～ 5,000円", "reward": "飲食金額の50%（最大6,000P）", "url": "https://pc.moppy.jp/fukumoni/item_transfer.php?item_url=https://www.fancrew.jp/detail2-oem/2504436?classicFlg=false", "lat": 35.732742, "lng": 139.714615}, {"name": "鶴亀八番 三ノ宮駅前店", "address": "兵庫県神戸市中央区北長狭通1-2-3 二鶴ビル地下 1F", "budget": "平均予算 2,000 ～ 3,000円", "reward": "飲食金額の50%（最大3,000P）", "url": "https://pc.moppy.jp/fukumoni/item_transfer.php?item_url=https://www.fancrew.jp/detail2-oem/2504633?classicFlg=false", "lat": 34.693928, "lng": 135.193192}, {"name": "鉄ぱん屋 弁兵衛 新天地店", "address": "広島県広島市中区新天地1-2", "budget": "平均予算 3,000 ～ 4,000円", "reward": "飲食金額の50%（最大5,500P）", "url": "https://pc.moppy.jp/fukumoni/item_transfer.php?item_url=https://www.fancrew.jp/detail2-oem/2501380?classicFlg=false", "lat": 34.391998, "lng": 132.463608}, {"name": "幕張ベイパーク 彦酉", "address": "千葉県千葉市美浜区若葉3-2-7-2 ヴィレッジⅥ", "budget": "平均予算 3,000 ～ 4,000円", "reward": "飲食金額の50%（最大5,000P）", "url": "https://pc.moppy.jp/fukumoni/item_transfer.php?item_url=https://www.fancrew.jp/detail2-oem/2504325?classicFlg=false", "lat": 35.647606, "lng": 140.04808}, {"name": "かんぱい家 葛西店", "address": "東京都江戸川区中葛西5-33-9", "budget": "平均予算 3,000 ～ 4,500円", "reward": "飲食金額の50%（最大4,500P）", "url": "https://pc.moppy.jp/fukumoni/item_transfer.php?item_url=https://www.fancrew.jp/detail2-oem/2502346?classicFlg=false", "lat": 35.663231, "lng": 139.87178}, {"name": "じゅらく 上野駅前店", "address": "東京都台東区上野6-11-11", "budget": "平均予算 1,000 ～ 2,000円", "reward": "飲食金額の30%（最大10,000P）", "url": "https://pc.moppy.jp/fukumoni/item_transfer.php?item_url=https://www.fancrew.jp/detail2-oem/2504166?classicFlg=false", "lat": 35.711468, "lng": 139.774734}, {"name": "PISOLA 名古屋丹後通店", "address": "愛知県名古屋市南区丹後通3丁目1", "budget": "平均予算 1,000 ～ 2,000円", "reward": "飲食金額の30%（最大5,000P）", "url": "https://pc.moppy.jp/fukumoni/item_transfer.php?item_url=https://www.fancrew.jp/detail2-oem/2500633?classicFlg=false", "lat": 35.07708, "lng": 136.922668}, {"name": "BABY FACE PLANET'S 名張店", "address": "三重県名張市夏見279-4", "budget": "平均予算 2,000 ～ 3,000円", "reward": "飲食金額の100%（最大3,000P）", "url": "https://pc.moppy.jp/fukumoni/item_transfer.php?item_url=https://www.fancrew.jp/detail2-oem/2500424?classicFlg=false", "lat": 34.615486, "lng": 136.100204}, {"name": "肉汁餃子のダンダダン 広島えびす通り店", "address": "広島県広島市中区胡町5-10 たからやビル", "budget": "平均予算 3,000 ～ 4,000円", "reward": "飲食金額の50%（最大3,000P）", "url": "https://pc.moppy.jp/fukumoni/item_transfer.php?item_url=https://www.fancrew.jp/detail2-oem/2505581?classicFlg=false", "lat": 34.392723, "lng": 132.464249}, {"name": "炭火焼鳥とさか 掛川店", "address": "静岡県掛川市駅前8-6 牧野ビル2F", "budget": "平均予算 3,000 ～ 4,000円", "reward": "飲食金額の50%（最大5,000P）", "url": "https://pc.moppy.jp/fukumoni/item_transfer.php?item_url=https://www.fancrew.jp/detail2-oem/2504704?classicFlg=false", "lat": 34.770184, "lng": 138.015778}, {"name": "PISOLA 秦野店", "address": "神奈川県秦野市緑町13-15", "budget": "平均予算 1,000 ～ 2,000円", "reward": "飲食金額の30%（最大5,000P）", "url": "https://pc.moppy.jp/fukumoni/item_transfer.php?item_url=https://www.fancrew.jp/detail2-oem/2504593?classicFlg=false", "lat": 35.376507, "lng": 139.210251}, {"name": "南欧バル INATORA", "address": "宮城県仙台市青葉区一番町4-3-22 スマイルホテル仙台国分町1F", "budget": "平均予算 2,000 ～ 3,000円", "reward": "飲食金額の40%（最大3,000P）", "url": "https://pc.moppy.jp/fukumoni/item_transfer.php?item_url=https://www.fancrew.jp/detail2-oem/2510303?classicFlg=false", "lat": 38.26334, "lng": 140.871017}, {"name": "PISOLA 高槻大塚店", "address": "大阪府高槻市大塚町1丁目1-3", "budget": "平均予算 1,000 ～ 2,000円", "reward": "飲食金額の30%（最大5,000P）", "url": "https://pc.moppy.jp/fukumoni/item_transfer.php?item_url=https://www.fancrew.jp/detail2-oem/2500448?classicFlg=false", "lat": 34.827099, "lng": 135.63179}, {"name": "もと牛", "address": "兵庫県神戸市東灘区住吉本町1-3-12 中野ビル 2F", "budget": "平均予算 6,000 ～ 7,000円", "reward": "飲食金額の50%（最大8,000P）", "url": "https://pc.moppy.jp/fukumoni/item_transfer.php?item_url=https://www.fancrew.jp/detail2-oem/2504623?classicFlg=false", "lat": 34.720367, "lng": 135.260742}, {"name": "ステーキハウス88 美ら海店", "address": "沖縄県国頭郡本部町浦崎278-3", "budget": "平均予算 2,000 ～ 3,000円", "reward": "飲食金額の70%（最大1,000P）", "url": "https://pc.moppy.jp/fukumoni/item_transfer.php?item_url=https://www.fancrew.jp/detail2-oem/2507406?classicFlg=false", "lat": 26.676453, "lng": 127.890289}, {"name": "たまや肉店 三宮", "address": "兵庫県神戸市中央区北長狭通1-5-1 ニュー光陽ビル 6F", "budget": "平均予算 3,000 ～ 4,000円", "reward": "飲食金額の50%（最大4,000P）", "url": "https://pc.moppy.jp/fukumoni/item_transfer.php?item_url=https://www.fancrew.jp/detail2-oem/2504631?classicFlg=false", "lat": 34.693489, "lng": 135.19252}, {"name": "魚屋ちから", "address": "山梨県甲府市中央1-6-8 完幸ビル 1F", "budget": "平均予算 3,000 ～ 4,000円", "reward": "飲食金額の50%（最大8,000P）", "url": "https://pc.moppy.jp/fukumoni/item_transfer.php?item_url=https://www.fancrew.jp/detail2-oem/2501419?classicFlg=false", "lat": 35.660694, "lng": 138.569443}, {"name": "炉端とおでん 呼炉凪来 本八戸店", "address": "青森県八戸市十六日町21 十六日町テナントビル 1F・2F", "budget": "平均予算 3,000 ～ 4,000円", "reward": "飲食金額の80%（最大5,000P）", "url": "https://pc.moppy.jp/fukumoni/item_transfer.php?item_url=https://www.fancrew.jp/detail2-oem/2502231?classicFlg=false", "lat": 40.508186, "lng": 141.489517}, {"name": "紅とん 戸越銀座店", "address": "東京都品川区平塚1-8-20 美和ビル1F", "budget": "平均予算 2,000 ～ 3,000円", "reward": "飲食金額の30%（最大10,000P）", "url": "https://pc.moppy.jp/fukumoni/item_transfer.php?item_url=https://www.fancrew.jp/detail2-oem/2505263?classicFlg=false", "lat": 35.615501, "lng": 139.715027}, {"name": "PISOLA 八王子中野店", "address": "東京都八王子市中野町3052-4", "budget": "平均予算 1,000 ～ 2,000円", "reward": "飲食金額の30%（最大5,000P）", "url": "https://pc.moppy.jp/fukumoni/item_transfer.php?item_url=https://www.fancrew.jp/detail2-oem/2502982?classicFlg=false", "lat": 35.676308, "lng": 139.313431}, {"name": "かんぱい家 平井店", "address": "東京都江戸川区平井4-11-11", "budget": "平均予算 3,000 ～ 4,500円", "reward": "飲食金額の50%（最大4,500P）", "url": "https://pc.moppy.jp/fukumoni/item_transfer.php?item_url=https://www.fancrew.jp/detail2-oem/2502348?classicFlg=false", "lat": 35.706493, "lng": 139.843994}, {"name": "ステーキハウス88 北谷店", "address": "沖縄県中頭郡北谷町美浜9-17 at’s chatan 2F", "budget": "平均予算 2,000 ～ 3,000円", "reward": "飲食金額の50%（最大1,000P）", "url": "https://pc.moppy.jp/fukumoni/item_transfer.php?item_url=https://www.fancrew.jp/detail2-oem/2507397?classicFlg=false", "lat": 26.315735, "lng": 127.754196}, {"name": "りんぐ 阪神新在家店", "address": "兵庫県神戸市灘区新在家北町1-2-15", "budget": "平均予算 3,000 ～ 4,000円", "reward": "飲食金額の50%（最大5,000P）", "url": "https://pc.moppy.jp/fukumoni/item_transfer.php?item_url=https://www.fancrew.jp/detail2-oem/2505110?classicFlg=false", "lat": 34.710632, "lng": 135.240295}, {"name": "PISOLA 和歌山向店", "address": "和歌山県和歌山市向206-1", "budget": "平均予算 1,000 ～ 2,000円", "reward": "飲食金額の30%（最大5,000P）", "url": "https://pc.moppy.jp/fukumoni/item_transfer.php?item_url=https://www.fancrew.jp/detail2-oem/2500653?classicFlg=false", "lat": 34.255646, "lng": 135.144196}, {"name": "満マル 河内天美店", "address": "大阪府松原市天美東8-1-3", "budget": "平均予算 2,000 ～ 3,000円", "reward": "飲食金額の40%（最大10,000P）", "url": "https://pc.moppy.jp/fukumoni/item_transfer.php?item_url=https://www.fancrew.jp/detail2-oem/2505978?classicFlg=false", "lat": 34.586849, "lng": 135.53476}, {"name": "PISOLA 沼津店", "address": "静岡県沼津市三枚橋町14-1", "budget": "平均予算 1,000 ～ 2,000円", "reward": "飲食金額の30%（最大5,000P）", "url": "https://pc.moppy.jp/fukumoni/item_transfer.php?item_url=https://www.fancrew.jp/detail2-oem/2507637?classicFlg=false", "lat": 35.099434, "lng": 138.86235}, {"name": "串焼きと煮野菜 下北沢の零や", "address": "東京都世田谷区北沢2丁目34-8 北沢KMビル2F A号", "budget": "平均予算 3,000 ～ 4,000円", "reward": "飲食金額の40%（最大5,000P）", "url": "https://pc.moppy.jp/fukumoni/item_transfer.php?item_url=https://www.fancrew.jp/detail2-oem/2506416?classicFlg=false", "lat": 35.663464, "lng": 139.668564}, {"name": "BAR JISTA", "address": "愛知県名古屋市中区栄3-12-6 インペリアルプラザ2F", "budget": "平均予算 2,000 ～ 3,000円", "reward": "飲食金額の50%（最大5,000P）", "url": "https://pc.moppy.jp/fukumoni/item_transfer.php?item_url=https://www.fancrew.jp/detail2-oem/2504371?classicFlg=false", "lat": 35.166573, "lng": 136.904251}, {"name": "鉄ぱん屋 弁兵衛 八丁堀店", "address": "広島県広島市中区八丁堀16-2", "budget": "平均予算 3,000 ～ 4,000円", "reward": "飲食金額の50%（最大5,500P）", "url": "https://pc.moppy.jp/fukumoni/item_transfer.php?item_url=https://www.fancrew.jp/detail2-oem/2501381?classicFlg=false", "lat": 34.394638, "lng": 132.462494}, {"name": "紅とん 飯田橋東口店", "address": "東京都千代田区飯田橋4-7-8 第3山商ビルiタワー B１F", "budget": "平均予算 2,000 ～ 3,000円", "reward": "飲食金額の30%（最大10,000P）", "url": "https://pc.moppy.jp/fukumoni/item_transfer.php?item_url=https://www.fancrew.jp/detail2-oem/2506767?classicFlg=false", "lat": 35.701107, "lng": 139.746307}, {"name": "PISOLA 真美ヶ丘店", "address": "奈良県北葛城郡広陵町馬見北9-12-9", "budget": "平均予算 1,000 ～ 2,000円", "reward": "飲食金額の30%（最大5,000P）", "url": "https://pc.moppy.jp/fukumoni/item_transfer.php?item_url=https://www.fancrew.jp/detail2-oem/2502985?classicFlg=false", "lat": 34.552956, "lng": 135.722076}, {"name": "紅とん 上野御徒町店", "address": "東京都台東区上野 6-2-5", "budget": "平均予算 2,000 ～ 3,000円", "reward": "飲食金額の30%（最大10,000P）", "url": "https://pc.moppy.jp/fukumoni/item_transfer.php?item_url=https://www.fancrew.jp/detail2-oem/2505278?classicFlg=false", "lat": 35.708195, "lng": 139.775406}, {"name": "PISOLA 川越的場店", "address": "埼玉県川越市的場833-1", "budget": "平均予算 1,000 ～ 2,000円", "reward": "飲食金額の30%（最大5,000P）", "url": "https://pc.moppy.jp/fukumoni/item_transfer.php?item_url=https://www.fancrew.jp/detail2-oem/2509614?classicFlg=false", "lat": 35.914272, "lng": 139.432556}, {"name": "PISOLA 松阪宮町店", "address": "三重県松阪市宮町233-4", "budget": "平均予算 1,000 ～ 2,000円", "reward": "飲食金額の50%（最大3,000P）", "url": "https://pc.moppy.jp/fukumoni/item_transfer.php?item_url=https://www.fancrew.jp/detail2-oem/2500639?classicFlg=false", "lat": 34.575779, "lng": 136.541992}, {"name": "PISOLA 近江八幡店", "address": "滋賀県近江八幡市鷹飼町北1丁目9-12", "budget": "平均予算 1,000 ～ 2,000円", "reward": "飲食金額の50%（最大3,000P）", "url": "https://pc.moppy.jp/fukumoni/item_transfer.php?item_url=https://www.fancrew.jp/detail2-oem/2503340?classicFlg=false", "lat": 35.128502, "lng": 136.106308}, {"name": "やきとんうまいもん横丁 まるたか 北千住店", "address": "東京都足立区千住2-65 須田ビル 1F", "budget": "平均予算 3,000 ～ 4,000円", "reward": "飲食金額の50%（最大4,000P）", "url": "https://pc.moppy.jp/fukumoni/item_transfer.php?item_url=https://www.fancrew.jp/detail2-oem/2501976?classicFlg=false", "lat": 35.748703, "lng": 139.803726}, {"name": "オリオン餃子 本店", "address": "栃木県宇都宮市曲師町2-12", "budget": "平均予算 2,000 ～ 3,000円", "reward": "飲食金額の50%（最大4,000P）", "url": "https://pc.moppy.jp/fukumoni/item_transfer.php?item_url=https://www.fancrew.jp/detail2-oem/2503287?classicFlg=false", "lat": 36.560215, "lng": 139.884293}, {"name": "雪月風花 本店", "address": "兵庫県神戸市中央区三宮町1丁目10-1 神戸交通センタービル10F", "budget": "平均予算 5,000 ～ 6,000円", "reward": "飲食金額の100%（最大5,000P）", "url": "https://pc.moppy.jp/fukumoni/item_transfer.php?item_url=https://www.fancrew.jp/detail2-oem/2504618?classicFlg=false", "lat": 34.693146, "lng": 135.193771}, {"name": "港町ブルース", "address": "兵庫県神戸市中央区北長狭通1-6-11", "budget": "平均予算 2,000 ～ 3,000円", "reward": "飲食金額の50%（最大5,000P）", "url": "https://pc.moppy.jp/fukumoni/item_transfer.php?item_url=https://www.fancrew.jp/detail2-oem/2501804?classicFlg=false", "lat": 34.69342, "lng": 135.192154}, {"name": "うみさと", "address": "福岡県福岡市中央区赤坂1丁目11-1 プロスパー赤坂1階", "budget": "平均予算 4,000 ～ 5,000円", "reward": "飲食金額の50%（最大4,000P）", "url": "https://pc.moppy.jp/fukumoni/item_transfer.php?item_url=https://www.fancrew.jp/detail2-oem/2505612?classicFlg=false", "lat": 33.588051, "lng": 130.390121}, {"name": "大衆酒場 なんで、や 豊洲店", "address": "東京都江東区豊洲3-2-20 豊洲フロント 1F", "budget": "平均予算 2,000 ～ 3,000円", "reward": "飲食金額の50%（最大5,000P）", "url": "https://pc.moppy.jp/fukumoni/item_transfer.php?item_url=https://www.fancrew.jp/detail2-oem/2508029?classicFlg=false", "lat": 35.656315, "lng": 139.795486}, {"name": "NITRO", "address": "愛知県名古屋市中区金山2-16-17 藤一番金山ビル 2F", "budget": "平均予算 2,000 ～ 3,000円", "reward": "飲食金額の50%（最大5,000P）", "url": "https://pc.moppy.jp/fukumoni/item_transfer.php?item_url=https://www.fancrew.jp/detail2-oem/2504372?classicFlg=false", "lat": 35.14444, "lng": 136.903198}, {"name": "炭火焼鳥とさか 日吉町駅前店", "address": "静岡県静岡市葵区横田町2-1 横田町ビル 1F", "budget": "平均予算 3,000 ～ 4,000円", "reward": "飲食金額の50%（最大5,000P）", "url": "https://pc.moppy.jp/fukumoni/item_transfer.php?item_url=https://www.fancrew.jp/detail2-oem/2504714?classicFlg=false", "lat": 34.97628, "lng": 138.392807}, {"name": "皆様酒場 立呑み 昭和ゴールデン 三宮店", "address": "兵庫県神戸市中央区北長狭通1-6-3", "budget": "平均予算 1,000 ～ 2,000円", "reward": "飲食金額の50%（最大5,000P）", "url": "https://pc.moppy.jp/fukumoni/item_transfer.php?item_url=https://www.fancrew.jp/detail2-oem/2501823?classicFlg=false", "lat": 34.693306, "lng": 135.192047}, {"name": "金のジンギ 新宿店", "address": "東京都新宿区西新宿1-19-13 青鈴ビルB1", "budget": "平均予算 3,000 ～ 4,000円", "reward": "飲食金額の50%（最大4,000P）", "url": "https://pc.moppy.jp/fukumoni/item_transfer.php?item_url=https://www.fancrew.jp/detail2-oem/2501365?classicFlg=false", "lat": 35.688404, "lng": 139.696884}, {"name": "炭火焼鳥とさか 静岡南口店", "address": "静岡県静岡市駿河区南町14-25 エスパティオ101", "budget": "平均予算 3,000 ～ 4,000円", "reward": "飲食金額の50%（最大5,000P）", "url": "https://pc.moppy.jp/fukumoni/item_transfer.php?item_url=https://www.fancrew.jp/detail2-oem/2504702?classicFlg=false", "lat": 34.970566, "lng": 138.390167}, {"name": "居酒屋革命 酔っ手羽 本厚木店", "address": "神奈川県厚木市中町2-1-1 LYMビル 2F", "budget": "平均予算 2,000 ～ 3,000円", "reward": "飲食金額の50%（最大6,000P）", "url": "https://pc.moppy.jp/fukumoni/item_transfer.php?item_url=https://www.fancrew.jp/detail2-oem/2505337?classicFlg=false", "lat": 35.438862, "lng": 139.363388}, {"name": "紅とん 田町店", "address": "東京都港区芝 5-16-7 芝ビル 1F", "budget": "平均予算 2,000 ～ 3,000円", "reward": "飲食金額の30%（最大10,000P）", "url": "https://pc.moppy.jp/fukumoni/item_transfer.php?item_url=https://www.fancrew.jp/detail2-oem/2505272?classicFlg=false", "lat": 35.648643, "lng": 139.746155}, {"name": "大衆イタリアンかね子 池袋店", "address": "東京都豊島区南池袋2-23-4 富沢ビル 1F", "budget": "平均予算 3,000 ～ 4,000円", "reward": "飲食金額の50%（最大4,000P）", "url": "https://pc.moppy.jp/fukumoni/item_transfer.php?item_url=https://www.fancrew.jp/detail2-oem/2503650?classicFlg=false", "lat": 35.727772, "lng": 139.713654}, {"name": "PISOLA 大和郡山筒井店", "address": "奈良県大和郡山市筒井町531-1", "budget": "平均予算 1,000 ～ 2,000円", "reward": "飲食金額の30%（最大5,000P）", "url": "https://pc.moppy.jp/fukumoni/item_transfer.php?item_url=https://www.fancrew.jp/detail2-oem/2502457?classicFlg=false", "lat": 34.620102, "lng": 135.776688}, {"name": "居酒屋革命 酔っ手羽 大阪天満店", "address": "大阪府大阪市北区天神橋5-1-17 1F・2F", "budget": "平均予算 2,000 ～ 3,000円", "reward": "飲食金額の50%（最大6,000P）", "url": "https://pc.moppy.jp/fukumoni/item_transfer.php?item_url=https://www.fancrew.jp/detail2-oem/2505341?classicFlg=false", "lat": 34.706509, "lng": 135.51207}, {"name": "シーシャカフェ＆バー musch 池袋東口店", "address": "東京都豊島区東池袋1丁目23-9 スタック池袋 2F", "budget": "平均予算 3,500 ～ 4,500円", "reward": "飲食金額の50%（最大5,000P）", "url": "https://pc.moppy.jp/fukumoni/item_transfer.php?item_url=https://www.fancrew.jp/detail2-oem/2502144?classicFlg=false", "lat": 35.729328, "lng": 139.715866}, {"name": "ステーキハウス88 国際通り西口店", "address": "沖縄県那覇市松尾1-4-3 永昇商事ビル2F", "budget": "平均予算 2,000 ～ 3,000円", "reward": "飲食金額の30%（最大1,000P）", "url": "https://pc.moppy.jp/fukumoni/item_transfer.php?item_url=https://www.fancrew.jp/detail2-oem/2507411?classicFlg=false", "lat": 26.214573, "lng": 127.683289}, {"name": "鉄ぱん屋 弁兵衛 福山駅前店", "address": "広島県福山市延広町3-7", "budget": "平均予算 3,000 ～ 4,000円", "reward": "飲食金額の50%（最大5,500P）", "url": "https://pc.moppy.jp/fukumoni/item_transfer.php?item_url=https://www.fancrew.jp/detail2-oem/2501387?classicFlg=false", "lat": 34.485878, "lng": 133.365005}, {"name": "肉バル ガブット 近江八幡店", "address": "滋賀県近江八幡市鷹飼町572 エミール近江八幡 壱番館1F", "budget": "平均予算 3,000 ～ 4,000円", "reward": "飲食金額の40%（最大5,000P）", "url": "https://pc.moppy.jp/fukumoni/item_transfer.php?item_url=https://www.fancrew.jp/detail2-oem/2504924?classicFlg=false", "lat": 35.122707, "lng": 136.1017}, {"name": "浅草聚楽", "address": "東京都台東区浅草1-23-9", "budget": "平均予算 1,000 ～ 2,000円", "reward": "飲食金額の30%（最大10,000P）", "url": "https://pc.moppy.jp/fukumoni/item_transfer.php?item_url=https://www.fancrew.jp/detail2-oem/2504167?classicFlg=false", "lat": 35.712276, "lng": 139.793793}, {"name": "PISOLA 茨木真砂店", "address": "大阪府茨木市真砂2丁目9-36", "budget": "平均予算 1,000 ～ 2,000円", "reward": "飲食金額の30%（最大5,000P）", "url": "https://pc.moppy.jp/fukumoni/item_transfer.php?item_url=https://www.fancrew.jp/detail2-oem/2500644?classicFlg=false", "lat": 34.799789, "lng": 135.580505}, {"name": "立ち呑み よりみち ノスタルジア", "address": "兵庫県神戸市灘区岩屋北町5-2-32 サニーハウス灘 1F", "budget": "平均予算 3,000 ～ 4,000円", "reward": "飲食金額の50%（最大5,000P）", "url": "https://pc.moppy.jp/fukumoni/item_transfer.php?item_url=https://www.fancrew.jp/detail2-oem/2505111?classicFlg=false", "lat": 34.704468, "lng": 135.216827}, {"name": "ステーキハウス88Jr. サンプラザ糸満店", "address": "沖縄県糸満市兼城400", "budget": "平均予算 2,000 ～ 3,000円", "reward": "飲食金額の50%（最大1,000P）", "url": "https://pc.moppy.jp/fukumoni/item_transfer.php?item_url=https://www.fancrew.jp/detail2-oem/2507414?classicFlg=false", "lat": 26.139912, "lng": 127.672592}, {"name": "日本酒とりまる 浦安店", "address": "千葉県浦安市北栄1-16-18 浦安ケルンビル 3F", "budget": "平均予算 2,000 ～ 3,000円", "reward": "飲食金額の50%（最大6,000P）", "url": "https://pc.moppy.jp/fukumoni/item_transfer.php?item_url=https://www.fancrew.jp/detail2-oem/2505994?classicFlg=false", "lat": 35.665482, "lng": 139.893265}, {"name": "PISOLA 半田店", "address": "愛知県半田市成岩東町23-1", "budget": "平均予算 1,000 ～ 2,000円", "reward": "飲食金額の50%（最大3,000P）", "url": "https://pc.moppy.jp/fukumoni/item_transfer.php?item_url=https://www.fancrew.jp/detail2-oem/2502214?classicFlg=false", "lat": 34.880543, "lng": 136.924805}, {"name": "きやり 神田明神前店", "address": "東京都千代田区外神田2-18-12 タイメイビル1F・B1F", "budget": "平均予算 2,000 ～ 3,000円", "reward": "飲食金額の30%（最大10,000P）", "url": "https://pc.moppy.jp/fukumoni/item_transfer.php?item_url=https://www.fancrew.jp/detail2-oem/2504178?classicFlg=false", "lat": 35.701393, "lng": 139.767303}, {"name": "網元・海鮮居酒屋 御酒印船 仙台店", "address": "宮城県仙台市青葉区中央3-1-24 荘内銀行ビルB1", "budget": "平均予算 3,000 ～ 4,000円", "reward": "飲食金額の30%（最大10,000P）", "url": "https://pc.moppy.jp/fukumoni/item_transfer.php?item_url=https://www.fancrew.jp/detail2-oem/2504168?classicFlg=false", "lat": 38.260571, "lng": 140.878891}, {"name": "満マル あびこ店", "address": "大阪府大阪市住吉区苅田5-19-7", "budget": "平均予算 2,000 ～ 3,000円", "reward": "飲食金額の40%（最大10,000P）", "url": "https://pc.moppy.jp/fukumoni/item_transfer.php?item_url=https://www.fancrew.jp/detail2-oem/2505976?classicFlg=false", "lat": 34.599873, "lng": 135.513519}, {"name": "炭火焼鳥・唐揚げ・釜めし 四代目鳥七庭", "address": "愛知県豊川市正岡町流田508", "budget": "平均予算 3,000 ～ 4,000円", "reward": "飲食金額の50%（最大5,000P）", "url": "https://pc.moppy.jp/fukumoni/item_transfer.php?item_url=https://www.fancrew.jp/detail2-oem/2507658?classicFlg=false", "lat": 34.802139, "lng": 137.386719}, {"name": "ラムゴロー 神田南口店", "address": "東京都千代田区鍛冶町1-3-7 蛇の目ビル 1F・2F", "budget": "平均予算 3,000 ～ 4,000円", "reward": "飲食金額の30%（最大5,000P）", "url": "https://pc.moppy.jp/fukumoni/item_transfer.php?item_url=https://www.fancrew.jp/detail2-oem/2501240?classicFlg=false", "lat": 35.690182, "lng": 139.770706}, {"name": "喰切じろう 袋町店", "address": "広島県広島市中区袋町4-35 千鳥ビル 1F", "budget": "平均予算 4,000 ～ 5,000円", "reward": "飲食金額の40%（最大4,000P）", "url": "https://pc.moppy.jp/fukumoni/item_transfer.php?item_url=https://www.fancrew.jp/detail2-oem/2505585?classicFlg=false", "lat": 34.392479, "lng": 132.457825}, {"name": "てんぷぅ 四条河原町店", "address": "京都府京都市中京区米屋町３７６－２ 2F", "budget": "平均予算 2,000 ～ 3,000円", "reward": "飲食金額の50%（最大4,000P）", "url": "https://pc.moppy.jp/fukumoni/item_transfer.php?item_url=https://www.fancrew.jp/detail2-oem/2503355?classicFlg=false", "lat": 35.004738, "lng": 135.769653}, {"name": "居酒屋革命 酔っ手羽 浜松店", "address": "静岡県浜松市中央区鍛冶町319-18 KO-BUILDING 1F～2F", "budget": "平均予算 2,000 ～ 3,000円", "reward": "飲食金額の50%（最大6,000P）", "url": "https://pc.moppy.jp/fukumoni/item_transfer.php?item_url=https://www.fancrew.jp/detail2-oem/2507329?classicFlg=false", "lat": 34.705803, "lng": 137.729889}, {"name": "⼤⼈の⾁バル ワラカルネ 津⽥沼店", "address": "千葉県船橋市前原西2-13-24 SKDビル 2F", "budget": "平均予算 4,000 ～ 5,000円", "reward": "飲食金額の40%（最大10,000P）", "url": "https://pc.moppy.jp/fukumoni/item_transfer.php?item_url=https://www.fancrew.jp/detail2-oem/2507102?classicFlg=false", "lat": 35.69294, "lng": 140.021362}, {"name": "日本酒とりまる 上野店", "address": "東京都台東区上野6-11-4", "budget": "平均予算 2,000 ～ 3,000円", "reward": "飲食金額の50%（最大6,000P）", "url": "https://pc.moppy.jp/fukumoni/item_transfer.php?item_url=https://www.fancrew.jp/detail2-oem/2505993?classicFlg=false", "lat": 35.710701, "lng": 139.774536}, {"name": "NICK HOUSE", "address": "山口県山口市小郡下郷1357-1", "budget": "平均予算 4,000 ～ 5,000円", "reward": "飲食金額の40%（最大4,000P）", "url": "https://pc.moppy.jp/fukumoni/item_transfer.php?item_url=https://www.fancrew.jp/detail2-oem/2505580?classicFlg=false", "lat": 34.098232, "lng": 131.394684}, {"name": "紅とん 日本橋本店", "address": "東京都中央区日本橋 2-2-20 日本橋仲通りビル", "budget": "平均予算 2,000 ～ 3,000円", "reward": "飲食金額の30%（最大10,000P）", "url": "https://pc.moppy.jp/fukumoni/item_transfer.php?item_url=https://www.fancrew.jp/detail2-oem/2505271?classicFlg=false", "lat": 35.682121, "lng": 139.771912}, {"name": "トロ壱 仙台一番町店", "address": "宮城県仙台市青葉区一番町2-5-5 東一中央ビル B1F", "budget": "平均予算 2,000 ～ 3,000円", "reward": "飲食金額の50%（最大6,000P）", "url": "https://pc.moppy.jp/fukumoni/item_transfer.php?item_url=https://www.fancrew.jp/detail2-oem/2509758?classicFlg=false", "lat": 38.259079, "lng": 140.872406}, {"name": "酒場五郎 神田西口店", "address": "東京都千代田区内神田3-4-6 富士エレベータービル", "budget": "平均予算 3,000 ～ 4,000円", "reward": "飲食金額の30%（最大5,000P）", "url": "https://pc.moppy.jp/fukumoni/item_transfer.php?item_url=https://www.fancrew.jp/detail2-oem/2501239?classicFlg=false", "lat": 35.690384, "lng": 139.769089}, {"name": "鶴屋 溝の口駅前店", "address": "神奈川県川崎市高津区溝口1-12-1 大久保ビル 2F", "budget": "平均予算 3,000 ～ 4,000円", "reward": "飲食金額の50%（最大5,000P）", "url": "https://pc.moppy.jp/fukumoni/item_transfer.php?item_url=https://www.fancrew.jp/detail2-oem/2503672?classicFlg=false", "lat": 35.600491, "lng": 139.612717}, {"name": "才色兼備", "address": "東京都墨田区江東橋2-14-1 サガノビル 1F", "budget": "平均予算 10,000 ～ 11,000円", "reward": "飲食金額の30%（最大15,000P）", "url": "https://pc.moppy.jp/fukumoni/item_transfer.php?item_url=https://www.fancrew.jp/detail2-oem/2505415?classicFlg=false", "lat": 35.695656, "lng": 139.811142}, {"name": "ステーキハウス88 松尾店", "address": "沖縄県那覇市松尾2-5-1 松尾124区ビル2F", "budget": "平均予算 2,000 ～ 3,000円", "reward": "飲食金額の30%（最大1,000P）", "url": "https://pc.moppy.jp/fukumoni/item_transfer.php?item_url=https://www.fancrew.jp/detail2-oem/2507412?classicFlg=false", "lat": 26.215147, "lng": 127.684914}, {"name": "炭火やBB 麻生店", "address": "北海道札幌市北区麻生町6丁目8-1", "budget": "平均予算 2,000 ～ 3,000円", "reward": "飲食金額の50%（最大5,000P）", "url": "https://pc.moppy.jp/fukumoni/item_transfer.php?item_url=https://www.fancrew.jp/detail2-oem/2509741?classicFlg=false", "lat": 43.111649, "lng": 141.340393}, {"name": "ステーキハウス88Jr. 浦添パルコシティ店", "address": "沖縄県浦添市西洲3丁目1-1", "budget": "平均予算 2,000 ～ 3,000円", "reward": "飲食金額の30%（最大1,000P）", "url": "https://pc.moppy.jp/fukumoni/item_transfer.php?item_url=https://www.fancrew.jp/detail2-oem/2507400?classicFlg=false", "lat": 26.260212, "lng": 127.695946}, {"name": "居酒屋革命 酔っ手羽 熊本下通店", "address": "熊本県熊本市中央区下通2-1-32 ODA下通ビル 1F・2F・3F", "budget": "平均予算 2,000 ～ 3,000円", "reward": "飲食金額の50%（最大6,000P）", "url": "https://pc.moppy.jp/fukumoni/item_transfer.php?item_url=https://www.fancrew.jp/detail2-oem/2505329?classicFlg=false", "lat": 32.799667, "lng": 130.707962}, {"name": "炭火やBB 琴似店", "address": "北海道札幌市西区琴似1条2丁目5-3 ハシモトビル1F", "budget": "平均予算 2,000 ～ 3,000円", "reward": "飲食金額の50%（最大5,000P）", "url": "https://pc.moppy.jp/fukumoni/item_transfer.php?item_url=https://www.fancrew.jp/detail2-oem/2504062?classicFlg=false", "lat": 43.078671, "lng": 141.306152}, {"name": "酔っ手羽 岐阜駅前店", "address": "岐阜県岐阜市住田町1-8", "budget": "平均予算 2,000 ～ 3,000円", "reward": "飲食金額の50%（最大6,000P）", "url": "https://pc.moppy.jp/fukumoni/item_transfer.php?item_url=https://www.fancrew.jp/detail2-oem/2505325?classicFlg=false", "lat": 35.41188, "lng": 136.758316}, {"name": "味の牛たん 喜助 エスパル店", "address": "宮城県仙台市青葉区中央1-1-1 エスパル仙台店B1F", "budget": "平均予算 2,500 ～ 3,000円", "reward": "飲食金額の50%（最大2,500P）", "url": "https://pc.moppy.jp/fukumoni/item_transfer.php?item_url=https://www.fancrew.jp/detail2-oem/2500310?classicFlg=false", "lat": 38.260338, "lng": 140.881699}, {"name": "紅とん 曙橋通店", "address": "東京都新宿区住吉町5-4 クオレ曙橋", "budget": "平均予算 2,000 ～ 3,000円", "reward": "飲食金額の30%（最大10,000P）", "url": "https://pc.moppy.jp/fukumoni/item_transfer.php?item_url=https://www.fancrew.jp/detail2-oem/2505273?classicFlg=false", "lat": 35.693462, "lng": 139.721008}, {"name": "肉バル ブッチャーズ 八百八 三軒茶屋店", "address": "東京都世田谷区三軒茶屋2-14-5", "budget": "平均予算 2,000 ～ 3,000円", "reward": "飲食金額の30%（最大10,000P）", "url": "https://pc.moppy.jp/fukumoni/item_transfer.php?item_url=https://www.fancrew.jp/detail2-oem/2504175?classicFlg=false", "lat": 35.642773, "lng": 139.668976}, {"name": "満マル 堺市駅前店", "address": "大阪府堺市北区北長尾町2-5-9", "budget": "平均予算 2,000 ～ 3,000円", "reward": "飲食金額の40%（最大10,000P）", "url": "https://pc.moppy.jp/fukumoni/item_transfer.php?item_url=https://www.fancrew.jp/detail2-oem/2505977?classicFlg=false", "lat": 34.576794, "lng": 135.499893}, {"name": "PISOLA 京都桂店", "address": "京都府京都市西京区川島調子町14番地", "budget": "平均予算 1,000 ～ 2,000円", "reward": "飲食金額の30%（最大5,000P）", "url": "https://pc.moppy.jp/fukumoni/item_transfer.php?item_url=https://www.fancrew.jp/detail2-oem/2500628?classicFlg=false", "lat": 34.973858, "lng": 135.699295}, {"name": "とりまる 町田店", "address": "東京都町田市原町田6-11-7 竹酔ビル", "budget": "平均予算 2,000 ～ 3,000円", "reward": "飲食金額の50%（最大6,000P）", "url": "https://pc.moppy.jp/fukumoni/item_transfer.php?item_url=https://www.fancrew.jp/detail2-oem/2505995?classicFlg=false", "lat": 35.544296, "lng": 139.445801}, {"name": "居酒屋革命 酔っ手羽 静岡両替町店", "address": "静岡県静岡市葵区両替町2-5-4 両替町プラザビル 1F", "budget": "平均予算 2,000 ～ 3,000円", "reward": "飲食金額の50%（最大6,000P）", "url": "https://pc.moppy.jp/fukumoni/item_transfer.php?item_url=https://www.fancrew.jp/detail2-oem/2508515?classicFlg=false", "lat": 34.973236, "lng": 138.383865}, {"name": "ステーキハウス88 那覇空港店", "address": "沖縄県那覇市鏡水150 際内連結ターミナルビル 3F", "budget": "平均予算 2,000 ～ 3,000円", "reward": "飲食金額の30%（最大1,000P）", "url": "https://pc.moppy.jp/fukumoni/item_transfer.php?item_url=https://www.fancrew.jp/detail2-oem/2507396?classicFlg=false", "lat": 26.210526, "lng": 127.649277}, {"name": "PISOLA 泉佐野店", "address": "大阪府泉佐野市鶴原1924-2", "budget": "平均予算 1,000 ～ 2,000円", "reward": "飲食金額の50%（最大3,000P）", "url": "https://pc.moppy.jp/fukumoni/item_transfer.php?item_url=https://www.fancrew.jp/detail2-oem/2500654?classicFlg=false", "lat": 34.425503, "lng": 135.344238}, {"name": "洋食＆スイーツ EVERY DAY BURG そごう千葉店", "address": "千葉県千葉市中央区新町1000 そごう千葉店 10F", "budget": "平均予算 1,000 ～ 2,000円", "reward": "飲食金額の35%（最大5,000P）", "url": "https://pc.moppy.jp/fukumoni/item_transfer.php?item_url=https://www.fancrew.jp/detail2-oem/2505416?classicFlg=false", "lat": 35.611118, "lng": 140.113571}, {"name": "ぼちぼち 本厚木店", "address": "神奈川県厚木市中町3-1-23", "budget": "平均予算 2,000 ～ 3,000円", "reward": "飲食金額の30%（最大10,000P）", "url": "https://pc.moppy.jp/fukumoni/item_transfer.php?item_url=https://www.fancrew.jp/detail2-oem/2505259?classicFlg=false", "lat": 35.439419, "lng": 139.363052}, {"name": "PISOLA 立川店", "address": "東京都立川市幸町2丁目25-5", "budget": "平均予算 1,000 ～ 2,000円", "reward": "飲食金額の30%（最大5,000P）", "url": "https://pc.moppy.jp/fukumoni/item_transfer.php?item_url=https://www.fancrew.jp/detail2-oem/2505647?classicFlg=false", "lat": 35.720978, "lng": 139.427979}, {"name": "紅とん 大井町店", "address": "東京都品川区東大井 5-4-16 フレンドヒル品川 1F", "budget": "平均予算 2,000 ～ 3,000円", "reward": "飲食金額の30%（最大10,000P）", "url": "https://pc.moppy.jp/fukumoni/item_transfer.php?item_url=https://www.fancrew.jp/detail2-oem/2505277?classicFlg=false", "lat": 35.607716, "lng": 139.736359}, {"name": "PISOLA 宇治小倉店", "address": "京都府宇治市小倉町久保119-2", "budget": "平均予算 1,000 ～ 2,000円", "reward": "飲食金額の30%（最大5,000P）", "url": "https://pc.moppy.jp/fukumoni/item_transfer.php?item_url=https://www.fancrew.jp/detail2-oem/2500627?classicFlg=false", "lat": 34.898624, "lng": 135.782837}, {"name": "SPIRAL Shibuya Branch", "address": "東京都渋谷区円山町14-2 福富ビル1F", "budget": "平均予算 6,000 ～ 7,000円", "reward": "飲食金額の50%（最大9,000P）", "url": "https://pc.moppy.jp/fukumoni/item_transfer.php?item_url=https://www.fancrew.jp/detail2-oem/2501148?classicFlg=false", "lat": 35.658203, "lng": 139.694305}, {"name": "串揚げじゅらく 新潟店", "address": "新潟県新潟市中央区東大通1-5-31 プレジール野中1F", "budget": "平均予算 2,000 ～ 3,000円", "reward": "飲食金額の30%（最大10,000P）", "url": "https://pc.moppy.jp/fukumoni/item_transfer.php?item_url=https://www.fancrew.jp/detail2-oem/2504184?classicFlg=false", "lat": 37.913841, "lng": 139.062057}, {"name": "PISOLA 明石魚住店", "address": "兵庫県明石市魚住町清水555", "budget": "平均予算 1,000 ～ 2,000円", "reward": "飲食金額の70%（最大3,000P）", "url": "https://pc.moppy.jp/fukumoni/item_transfer.php?item_url=https://www.fancrew.jp/detail2-oem/2500629?classicFlg=false", "lat": 34.702457, "lng": 134.910034}, {"name": "亜麺坊 新潟店", "address": "新潟県新潟市中央区花園1-1-1 新潟駅ビルCoCoLo 西館1F", "budget": "平均予算 2,000 ～ 3,000円", "reward": "飲食金額の30%（最大10,000P）", "url": "https://pc.moppy.jp/fukumoni/item_transfer.php?item_url=https://www.fancrew.jp/detail2-oem/2504181?classicFlg=false", "lat": 37.913288, "lng": 139.060867}, {"name": "ステーキハウス88 国際通り店", "address": "沖縄県那覇市牧志3-1-6 勉強堂ビル 2F", "budget": "平均予算 2,000 ～ 3,000円", "reward": "飲食金額の30%（最大1,000P）", "url": "https://pc.moppy.jp/fukumoni/item_transfer.php?item_url=https://www.fancrew.jp/detail2-oem/2507395?classicFlg=false", "lat": 26.216269, "lng": 127.688515}, {"name": "シーシャカフェ＆バー musch 梅田曽根崎店", "address": "大阪府大阪市北区小松原町1-27 梅田エビスビル2F", "budget": "平均予算 3,500 ～ 4,500円", "reward": "飲食金額の50%（最大5,000P）", "url": "https://pc.moppy.jp/fukumoni/item_transfer.php?item_url=https://www.fancrew.jp/detail2-oem/2502145?classicFlg=false", "lat": 34.702293, "lng": 135.501602}, {"name": "居酒屋革命 酔っ手羽 東岡崎店", "address": "愛知県岡崎市明大寺本町4-13 鈴正ビル1F", "budget": "平均予算 2,000 ～ 3,000円", "reward": "飲食金額の50%（最大6,000P）", "url": "https://pc.moppy.jp/fukumoni/item_transfer.php?item_url=https://www.fancrew.jp/detail2-oem/2505335?classicFlg=false", "lat": 34.952667, "lng": 137.165619}, {"name": "紅とん 神田神保町店", "address": "東京都千代田区神田神保町 1-21-3", "budget": "平均予算 2,000 ～ 3,000円", "reward": "飲食金額の30%（最大10,000P）", "url": "https://pc.moppy.jp/fukumoni/item_transfer.php?item_url=https://www.fancrew.jp/detail2-oem/2505275?classicFlg=false", "lat": 35.69529, "lng": 139.761002}, {"name": "イタリアン酒場56 神田駅前店", "address": "東京都千代田区内神田3-13-9 YK神田ビル 1F・2F", "budget": "平均予算 4,000 ～ 5,000円", "reward": "飲食金額の30%（最大8,000P）", "url": "https://pc.moppy.jp/fukumoni/item_transfer.php?item_url=https://www.fancrew.jp/detail2-oem/2507862?classicFlg=false", "lat": 35.69165, "lng": 139.770523}, {"name": "辻田家 真岡店", "address": "栃木県真岡市大谷本町7-20", "budget": "平均予算 1,000 ～ 2,000円", "reward": "飲食金額の50%（最大1,500P）", "url": "https://pc.moppy.jp/fukumoni/item_transfer.php?item_url=https://www.fancrew.jp/detail2-oem/2505099?classicFlg=false", "lat": 36.436298, "lng": 139.99704}, {"name": "紅とん 茅場町店", "address": "東京都中央区日本橋茅場町3-5-3 日宝茅場町ビル1F", "budget": "平均予算 2,000 ～ 3,000円", "reward": "飲食金額の30%（最大10,000P）", "url": "https://pc.moppy.jp/fukumoni/item_transfer.php?item_url=https://www.fancrew.jp/detail2-oem/2505260?classicFlg=false", "lat": 35.678196, "lng": 139.778687}, {"name": "はっぴ商店 おもちゃのまち店", "address": "栃木県下都賀郡壬生町幸町4-3-3", "budget": "平均予算 1,000 ～ 2,000円", "reward": "支払金額の50%（最大1,500P）", "url": "https://pc.moppy.jp/fukumoni/item_transfer.php?item_url=https://www.fancrew.jp/detail2-oem/2505100?classicFlg=false", "lat": 36.463425, "lng": 139.835999}, {"name": "紅とん 高田馬場店", "address": "東京都新宿区高田馬場 2-15-10 城北ビル 1F", "budget": "平均予算 2,000 ～ 3,000円", "reward": "飲食金額の30%（最大10,000P）", "url": "https://pc.moppy.jp/fukumoni/item_transfer.php?item_url=https://www.fancrew.jp/detail2-oem/2505274?classicFlg=false", "lat": 35.71344, "lng": 139.706085}, {"name": "炭火やBB 手稲店", "address": "北海道札幌市手稲区手稲本町1条3-3-10 千葉ビル B1F", "budget": "平均予算 2,000 ～ 3,000円", "reward": "飲食金額の50%（最大5,000P）", "url": "https://pc.moppy.jp/fukumoni/item_transfer.php?item_url=https://www.fancrew.jp/detail2-oem/2504064?classicFlg=false", "lat": 43.119648, "lng": 141.243576}, {"name": "炭火やBB すすきの店", "address": "北海道札幌市中央区南6条西4 ススキノ野口ビル 1F", "budget": "平均予算 2,000 ～ 3,000円", "reward": "飲食金額の50%（最大5,000P）", "url": "https://pc.moppy.jp/fukumoni/item_transfer.php?item_url=https://www.fancrew.jp/detail2-oem/2504061?classicFlg=false", "lat": 43.053185, "lng": 141.353134}, {"name": "とりひげ 支店", "address": "兵庫県神戸市灘区倉石通6-1-17", "budget": "平均予算 3,000 ～ 4,000円", "reward": "飲食金額の50%（最大5,000P）", "url": "https://pc.moppy.jp/fukumoni/item_transfer.php?item_url=https://www.fancrew.jp/detail2-oem/2505109?classicFlg=false", "lat": 34.712406, "lng": 135.220718}, {"name": "紅とん 上野ユースロード店", "address": "東京都台東区上野6-16-7 D・B上野Ⅱ", "budget": "平均予算 2,000 ～ 3,000円", "reward": "飲食金額の30%（最大10,000P）", "url": "https://pc.moppy.jp/fukumoni/item_transfer.php?item_url=https://www.fancrew.jp/detail2-oem/2505265?classicFlg=false", "lat": 35.710651, "lng": 139.776016}, {"name": "紅とん 御徒町南口店", "address": "東京都台東区上野5-20-3 JR高架下", "budget": "平均予算 2,000 ～ 3,000円", "reward": "飲食金額の30%（最大10,000P）", "url": "https://pc.moppy.jp/fukumoni/item_transfer.php?item_url=https://www.fancrew.jp/detail2-oem/2505280?classicFlg=false", "lat": 35.706108, "lng": 139.774384}, {"name": "わんこ手羽と親鳥のお店 かちてば栄駅前店", "address": "愛知県名古屋市中区錦3-17-5 EXIT NISHIKI は区画", "budget": "平均予算 2,000 ～ 3,000円", "reward": "飲食金額の30%（最大5,000P）", "url": "https://pc.moppy.jp/fukumoni/item_transfer.php?item_url=https://www.fancrew.jp/detail2-oem/2503899?classicFlg=false", "lat": 35.170654, "lng": 136.906143}, {"name": "焼野菜 銀河団", "address": "東京都世田谷区北沢2-6-6 澤田ビルB1 B号", "budget": "平均予算 3,000 ～ 4,000円", "reward": "飲食金額の40%（最大5,000P）", "url": "https://pc.moppy.jp/fukumoni/item_transfer.php?item_url=https://www.fancrew.jp/detail2-oem/2506417?classicFlg=false", "lat": 35.661667, "lng": 139.669037}, {"name": "紅とん 西葛西店", "address": "東京都江戸川区西葛西3-15-16 アイリスビル 1F", "budget": "平均予算 2,000 ～ 3,000円", "reward": "飲食金額の30%（最大10,000P）", "url": "https://pc.moppy.jp/fukumoni/item_transfer.php?item_url=https://www.fancrew.jp/detail2-oem/2505281?classicFlg=false", "lat": 35.66486, "lng": 139.858353}, {"name": "紅とん 浜松町金杉橋店", "address": "東京都港区浜松町 2-11-16 ユーワビル 1F・B1F", "budget": "平均予算 2,000 ～ 3,000円", "reward": "飲食金額の30%（最大10,000P）", "url": "https://pc.moppy.jp/fukumoni/item_transfer.php?item_url=https://www.fancrew.jp/detail2-oem/2505276?classicFlg=false", "lat": 35.653744, "lng": 139.755508}, {"name": "魚とん 西葛西店", "address": "東京都江戸川区西葛西6-7-2 メトロセンター西葛西西口 B棟ロ号", "budget": "平均予算 2,000 ～ 3,000円", "reward": "飲食金額の30%（最大10,000P）", "url": "https://pc.moppy.jp/fukumoni/item_transfer.php?item_url=https://www.fancrew.jp/detail2-oem/2505283?classicFlg=false", "lat": 35.664906, "lng": 139.856567}, {"name": "居酒屋革命 酔っ手羽 大阪高槻店", "address": "大阪府高槻市城北町2-3-8 入潮ビル1F", "budget": "平均予算 2,000 ～ 3,000円", "reward": "飲食金額の50%（最大6,000P）", "url": "https://pc.moppy.jp/fukumoni/item_transfer.php?item_url=https://www.fancrew.jp/detail2-oem/2505340?classicFlg=false", "lat": 34.849377, "lng": 135.62381}, {"name": "紅とん 新橋一丁目店", "address": "東京都港区新橋1-3-16", "budget": "平均予算 2,000 ～ 3,000円", "reward": "飲食金額の30%（最大10,000P）", "url": "https://pc.moppy.jp/fukumoni/item_transfer.php?item_url=https://www.fancrew.jp/detail2-oem/2505266?classicFlg=false", "lat": 35.668377, "lng": 139.758286}, {"name": "小籠包マニア 神田店", "address": "東京都千代田区鍛冶町1-2-13", "budget": "平均予算 3,000 ～ 4,000円", "reward": "飲食金額の30%（最大4,000P）", "url": "https://pc.moppy.jp/fukumoni/item_transfer.php?item_url=https://www.fancrew.jp/detail2-oem/2501241?classicFlg=false", "lat": 35.690022, "lng": 139.770508}, {"name": "辻田家 小山店", "address": "栃木県小山市西城南3-6-6", "budget": "平均予算 1,000 ～ 2,000円", "reward": "飲食金額の50%（最大1,500P）", "url": "https://pc.moppy.jp/fukumoni/item_transfer.php?item_url=https://www.fancrew.jp/detail2-oem/2505097?classicFlg=false", "lat": 36.298328, "lng": 139.80687}, {"name": "紅とん 門前仲町店", "address": "東京都江東区富岡1-1-14", "budget": "平均予算 2,000 ～ 3,000円", "reward": "飲食金額の30%（最大10,000P）", "url": "https://pc.moppy.jp/fukumoni/item_transfer.php?item_url=https://www.fancrew.jp/detail2-oem/2505264?classicFlg=false", "lat": 35.670483, "lng": 139.797485}, {"name": "紅とん 新橋二丁目店", "address": "東京都港区新橋2-3-6 中沢建物新橋ビル 2F", "budget": "平均予算 2,000 ～ 3,000円", "reward": "飲食金額の30%（最大10,000P）", "url": "https://pc.moppy.jp/fukumoni/item_transfer.php?item_url=https://www.fancrew.jp/detail2-oem/2505282?classicFlg=false", "lat": 35.66766, "lng": 139.755569}, {"name": "肉と日本酒バル ワラカド 津田沼店", "address": "千葉県習志野市津田沼1-3-11 2F", "budget": "平均予算 4,000 ～ 5,000円", "reward": "飲食金額の40%（最大8,000P）", "url": "https://pc.moppy.jp/fukumoni/item_transfer.php?item_url=https://www.fancrew.jp/detail2-oem/2505414?classicFlg=false", "lat": 35.690052, "lng": 140.022461}, {"name": "紅とん 大塚店", "address": "東京都豊島区南大塚3-50-5", "budget": "平均予算 2,000 ～ 3,000円", "reward": "飲食金額の30%（最大10,000P）", "url": "https://pc.moppy.jp/fukumoni/item_transfer.php?item_url=https://www.fancrew.jp/detail2-oem/2505261?classicFlg=false", "lat": 35.730331, "lng": 139.728333}, {"name": "PISOLA 岩出店", "address": "和歌山県岩出市中迫173", "budget": "平均予算 1,000 ～ 2,000円", "reward": "飲食金額の50%（最大5,000P）", "url": "https://pc.moppy.jp/fukumoni/item_transfer.php?item_url=https://www.fancrew.jp/detail2-oem/2500651?classicFlg=false", "lat": 34.261745, "lng": 135.313599}, {"name": "BABY FACE PLANET'S 名張店", "address": "三重県名張市夏見279-4", "budget": "平均予算 2,000 ～ 3,000円", "reward": "飲食金額の100%（最大3,000P）", "url": "https://pc.moppy.jp/fukumoni/item_transfer.php?item_url=https://www.fancrew.jp/detail2-oem/2500642?classicFlg=false", "lat": 34.615486, "lng": 136.100204}, {"name": "炭火やBB 琴似別邸店", "address": "北海道札幌市西区琴似1条5-4-17 ロイヤルホープビル B1F", "budget": "平均予算 2,000 ～ 3,000円", "reward": "飲食金額の50%（最大5,000P）", "url": "https://pc.moppy.jp/fukumoni/item_transfer.php?item_url=https://www.fancrew.jp/detail2-oem/2504063?classicFlg=false", "lat": 43.075806, "lng": 141.303024}, {"name": "プレミアム播州酒場", "address": "兵庫県姫路市立町4 立町クリスタルビル2F", "budget": "平均予算 3,000 ～ 4,000円", "reward": "飲食金額の50%（最大5,000P）", "url": "https://pc.moppy.jp/fukumoni/item_transfer.php?item_url=https://www.fancrew.jp/detail2-oem/2506239?classicFlg=false", "lat": 34.830112, "lng": 134.689651}, {"name": "みそら堂 鶴田店", "address": "栃木県宇都宮市鶴田町2967-1", "budget": "平均予算 1,000 ～ 2,000円", "reward": "飲食金額の50%（最大1,500P）", "url": "https://pc.moppy.jp/fukumoni/item_transfer.php?item_url=https://www.fancrew.jp/detail2-oem/2505093?classicFlg=false", "lat": 36.55233, "lng": 139.865219}, {"name": "辻田家 簗瀬店", "address": "栃木県宇都宮市簗瀬町1590-7", "budget": "平均予算 1,000 ～ 2,000円", "reward": "飲食金額の50%（最大1,500P）", "url": "https://pc.moppy.jp/fukumoni/item_transfer.php?item_url=https://www.fancrew.jp/detail2-oem/2505095?classicFlg=false", "lat": 36.54203, "lng": 139.890671}, {"name": "辻田家 石橋店", "address": "栃木県河内郡上三川町鞘堂123-7", "budget": "平均予算 1,000 ～ 2,000円", "reward": "飲食金額の50%（最大1,500P）", "url": "https://pc.moppy.jp/fukumoni/item_transfer.php?item_url=https://www.fancrew.jp/detail2-oem/2505098?classicFlg=false", "lat": 36.461647, "lng": 139.869705}, {"name": "居酒屋革命 酔っ手羽 熊本下通2号店", "address": "熊本県熊本市中央区下通1-2-11 TM34ビル 1F", "budget": "平均予算 2,000 ～ 3,000円", "reward": "飲食金額の50%（最大6,000P）", "url": "https://pc.moppy.jp/fukumoni/item_transfer.php?item_url=https://www.fancrew.jp/detail2-oem/2505328?classicFlg=false", "lat": 32.802109, "lng": 130.708267}, {"name": "炭火やBB 南3条店", "address": "北海道札幌市中央区南3条西4丁目 TOSHO3.4ビル2F・3F", "budget": "平均予算 2,000 ～ 3,000円", "reward": "飲食金額の50%（最大5,000P）", "url": "https://pc.moppy.jp/fukumoni/item_transfer.php?item_url=https://www.fancrew.jp/detail2-oem/2504065?classicFlg=false", "lat": 43.056576, "lng": 141.352249}, {"name": "シーシャカフェ＆バー musch 梅田HEP前店", "address": "大阪府大阪市北区角田町6-2 ラッキービル3F", "budget": "平均予算 3,500 ～ 4,500円", "reward": "飲食金額の50%（最大5,000P）", "url": "https://pc.moppy.jp/fukumoni/item_transfer.php?item_url=https://www.fancrew.jp/detail2-oem/2502146?classicFlg=false", "lat": 34.703621, "lng": 135.500916}, {"name": "石焼地どり おじぎ屋 加古川本店", "address": "兵庫県加古川市尾上町安田394-1", "budget": "平均予算 3,000 ～ 4,000円", "reward": "飲食金額の50%（最大4,000P）", "url": "https://pc.moppy.jp/fukumoni/item_transfer.php?item_url=https://www.fancrew.jp/detail2-oem/2504292?classicFlg=false", "lat": 34.747505, "lng": 134.834854}, {"name": "ちょい呑み 播州酒場", "address": "兵庫県姫路市駅前町308", "budget": "平均予算 3,000 ～ 4,000円", "reward": "飲食金額の50%（最大5,000P）", "url": "https://pc.moppy.jp/fukumoni/item_transfer.php?item_url=https://www.fancrew.jp/detail2-oem/2506240?classicFlg=false", "lat": 34.829098, "lng": 134.692093}, {"name": "辻田家 鶴田店", "address": "栃木県宇都宮市睦町7-3", "budget": "平均予算 1,000 ～ 2,000円", "reward": "飲食金額の50%（最大1,500P）", "url": "https://pc.moppy.jp/fukumoni/item_transfer.php?item_url=https://www.fancrew.jp/detail2-oem/2505096?classicFlg=false", "lat": 36.563427, "lng": 139.860596}, {"name": "Big Pig 神田カープ本店", "address": "東京都千代田区内神田3-4-6 富士エレベータービル B1F", "budget": "平均予算 3,000 ～ 4,000円", "reward": "飲食金額の30%（最大8,000P）", "url": "https://pc.moppy.jp/fukumoni/item_transfer.php?item_url=https://www.fancrew.jp/detail2-oem/2501236?classicFlg=false", "lat": 35.690384, "lng": 139.769089}, {"name": "焼き手羽居酒屋 かちてば", "address": "三重県四日市市西新地10-20", "budget": "平均予算 2,000 ～ 3,000円", "reward": "飲食金額の50%（最大3,000P）", "url": "https://pc.moppy.jp/fukumoni/item_transfer.php?item_url=https://www.fancrew.jp/detail2-oem/2503898?classicFlg=false", "lat": 34.968849, "lng": 136.620148}, {"name": "肉汁水餃子 餃包 六本木交差点", "address": "東京都港区六本木4丁目9-8", "budget": "平均予算 3,000 ～ 4,000円", "reward": "飲食金額の70%（最大8,000P）", "url": "https://pc.moppy.jp/fukumoni/item_transfer.php?item_url=https://www.fancrew.jp/detail2-oem/2505785?classicFlg=false", "lat": 35.663651, "lng": 139.732422}, {"name": "壬生蘭々亭", "address": "栃木県下都賀郡壬生町国谷1870-2", "budget": "平均予算 1,000 ～ 2,000円", "reward": "飲食金額の50%（最大1,500P）", "url": "https://pc.moppy.jp/fukumoni/item_transfer.php?item_url=https://www.fancrew.jp/detail2-oem/2505102?classicFlg=false", "lat": 36.45507, "lng": 139.808701}, {"name": "みそら堂 おもちゃのまち総本店", "address": "栃木県下都賀郡壬生町幸町4-3-3", "budget": "平均予算 1,000 ～ 2,000円", "reward": "飲食金額の50%（最大1,500P）", "url": "https://pc.moppy.jp/fukumoni/item_transfer.php?item_url=https://www.fancrew.jp/detail2-oem/2505094?classicFlg=false", "lat": 36.463425, "lng": 139.835999}], "updated": "2026-04-30T12:41:36.575768+09:00"}