{"stores": [{"name": "居酒屋 寅 すすきの店", "address": "北海道札幌市中央区南3条西4丁目2 石原ビル1階", "lat": 43.056313, "lng": 141.352371, "reward": "4,000円", "budget": "", "url": "https://www2.ms-r.com/MSR/MonitorNew/MyPage/EntryInput.asp?InvitationID=4334600"}, {"name": "粋な居酒屋　おいよ 南4条店", "address": "北海道札幌市中央区南4条西2丁目8−7　渡辺ビル 2F", "lat": 43.056221, "lng": 141.355637, "reward": "6,000円", "budget": "", "url": "https://www2.ms-r.com/MSR/MonitorNew/MyPage/EntryInput.asp?InvitationID=4276983"}, {"name": "粋な居酒屋　おいよ 別邸　南4条店", "address": "北海道札幌市中央区南４条西２第３１桂和ビル　２F", "lat": 43.055874, "lng": 141.355698, "reward": "6,000円", "budget": "", "url": "https://www2.ms-r.com/MSR/MonitorNew/MyPage/EntryInput.asp?InvitationID=4276985"}, {"name": "粋な居酒屋　おいよ 狸小路4丁目店", "address": "北海道札幌市中央区南2条西4丁目10-2　清水ビルB1", "lat": 43.057453, "lng": 141.352081, "reward": "6,000円", "budget": "", "url": "https://www2.ms-r.com/MSR/MonitorNew/MyPage/EntryInput.asp?InvitationID=4276987"}, {"name": "さかな 真心庵【宴会調査】", "address": "北海道札幌市中央区南十一条西20-1-5　", "lat": 43.044575, "lng": 141.328964, "reward": "14,000円", "budget": "", "url": "https://www2.ms-r.com/MSR/MonitorNew/MyPage/EntryInput.asp?InvitationID=4222167"}, {"name": "新時代 札幌北一条店", "address": "北海道札幌市中央区北1条西3丁目3−10Koko Hotel札幌駅前1階", "lat": 43.063015, "lng": 141.35228, "reward": "4,000円", "budget": "", "url": "https://www2.ms-r.com/MSR/MonitorNew/MyPage/EntryInput.asp?InvitationID=4269167"}, {"name": "新時代 札幌狸小路店", "address": "北海道札幌市中央区南3条西4丁目16-1 ワカツキSQUARE BLD2F", "lat": 43.056877, "lng": 141.352219, "reward": "4,000円", "budget": "", "url": "https://www2.ms-r.com/MSR/MonitorNew/MyPage/EntryInput.asp?InvitationID=4269218"}, {"name": "新時代 札幌麻生店", "address": "北海道札幌市北区麻生町3丁目10－10", "lat": 43.110027, "lng": 141.338516, "reward": "4,000円", "budget": "", "url": "https://www2.ms-r.com/MSR/MonitorNew/MyPage/EntryInput.asp?InvitationID=4269237"}, {"name": "わんたん亭 清田店", "address": "北海道札幌市清田区清田２条１丁目３-８", "lat": 43.006012, "lng": 141.42981, "reward": "1,000円", "budget": "", "url": "https://www2.ms-r.com/MSR/MonitorNew/MyPage/EntryInput.asp?InvitationID=4285435"}, {"name": "新時代 函館本町店", "address": "北海道函館市本町32-11", "lat": 41.788792, "lng": 140.751648, "reward": "4,000円", "budget": "", "url": "https://www2.ms-r.com/MSR/MonitorNew/MyPage/EntryInput.asp?InvitationID=4269210"}, {"name": "鮨処 魚一心 小樽五番街店", "address": "北海道小樽市築港11-5　ウィングベイ小樽五番街１F", "lat": 43.185925, "lng": 141.018311, "reward": "6,000円", "budget": "", "url": "https://www2.ms-r.com/MSR/MonitorNew/MyPage/EntryInput.asp?InvitationID=4222168"}, {"name": "新時代 青森クロスタワーAｰBAY店", "address": "青森県青森市長島1丁目6-6 クロスタワーAーBAY2", "lat": 40.823437, "lng": 140.74498, "reward": "4,000円", "budget": "", "url": "https://www2.ms-r.com/MSR/MonitorNew/MyPage/EntryInput.asp?InvitationID=4269195"}, {"name": "新時代 盛岡開運橋通り店", "address": "岩手県盛岡市開運橋通1−34", "lat": 39.702522, "lng": 141.144348, "reward": "4,000円", "budget": "", "url": "https://www2.ms-r.com/MSR/MonitorNew/MyPage/EntryInput.asp?InvitationID=4269177"}, {"name": "新時代 盛岡駅前店", "address": "岩手県盛岡市盛岡駅前通10-2 MORI BLDG.2Ｆ", "lat": 39.702354, "lng": 141.138824, "reward": "4,000円", "budget": "", "url": "https://www2.ms-r.com/MSR/MonitorNew/MyPage/EntryInput.asp?InvitationID=4269189"}, {"name": "新時代 岩手北上店", "address": "岩手県北上市青柳町2丁目1-12 マックスビル1F", "lat": 39.283916, "lng": 141.117615, "reward": "4,000円", "budget": "", "url": "https://www2.ms-r.com/MSR/MonitorNew/MyPage/EntryInput.asp?InvitationID=4269223"}, {"name": "新時代 秋田大町店", "address": "秋田県秋田市大町5丁目4-10 大町第2アジマックスビル1F", "lat": 39.714108, "lng": 140.114487, "reward": "4,000円", "budget": "", "url": "https://www2.ms-r.com/MSR/MonitorNew/MyPage/EntryInput.asp?InvitationID=4269222"}, {"name": "炉ばた", "address": "宮城県仙台市青葉区国分町2-10-28　YS-ビックビル1階B号室", "lat": 38.26437, "lng": 140.870041, "reward": "6,500円", "budget": "", "url": "https://www2.ms-r.com/MSR/MonitorNew/MyPage/EntryInput.asp?InvitationID=4220815"}, {"name": "新時代 仙台新伝馬町店", "address": "宮城県仙台市青葉区中央2-5-15", "lat": 38.261623, "lng": 140.875916, "reward": "4,000円", "budget": "", "url": "https://www2.ms-r.com/MSR/MonitorNew/MyPage/EntryInput.asp?InvitationID=4269153"}, {"name": "新時代 仙台国分町店", "address": "宮城県仙台市青葉区一番町4-4-10", "lat": 38.263729, "lng": 140.870316, "reward": "4,000円", "budget": "", "url": "https://www2.ms-r.com/MSR/MonitorNew/MyPage/EntryInput.asp?InvitationID=4269199"}, {"name": "新時代 仙台駅東口ヨドバシ店", "address": "宮城県仙台市宮城野区榴岡1-3-1 ﾖﾄﾞﾊﾞｼｶﾒﾗ第1ﾋﾞﾙ1階", "lat": 38.259232, "lng": 140.884476, "reward": "4,000円", "budget": "", "url": "https://www2.ms-r.com/MSR/MonitorNew/MyPage/EntryInput.asp?InvitationID=4269163"}, {"name": "道とん堀 石巻店", "address": "宮城県石巻市恵み野2-6-4　", "lat": 38.44334, "lng": 141.271622, "reward": "2,500円", "budget": "", "url": "https://www2.ms-r.com/MSR/MonitorNew/MyPage/EntryInput.asp?InvitationID=4325512"}, {"name": "新時代 山形駅前店", "address": "山形県山形市十日町1丁目1-35 リモージュ21ビル2F", "lat": 38.246494, "lng": 140.33342, "reward": "4,000円", "budget": "", "url": "https://www2.ms-r.com/MSR/MonitorNew/MyPage/EntryInput.asp?InvitationID=4269225"}, {"name": "新時代 福島駅西口店", "address": "福島県福島市太田町13-73 ｻﾞ･ｾﾚｸﾄﾝ福島 B1", "lat": 37.754887, "lng": 140.457275, "reward": "4,000円", "budget": "", "url": "https://www2.ms-r.com/MSR/MonitorNew/MyPage/EntryInput.asp?InvitationID=4269155"}, {"name": "新時代 福島いわき駅前店", "address": "福島県いわき市平白銀町1-1 不二屋第一ビルB1階", "lat": 37.056923, "lng": 140.893494, "reward": "4,000円", "budget": "", "url": "https://www2.ms-r.com/MSR/MonitorNew/MyPage/EntryInput.asp?InvitationID=4269182"}, {"name": "新時代 水戸駅南口店", "address": "茨城県水戸市城南1-4-12", "lat": 36.365955, "lng": 140.474899, "reward": "4,000円", "budget": "", "url": "https://www2.ms-r.com/MSR/MonitorNew/MyPage/EntryInput.asp?InvitationID=4269238"}, {"name": "焼肉トラジ つくば店", "address": "茨城県つくば市吾妻１丁目６−１ トナリエつくばスクエア キュート3F", "lat": 36.081863, "lng": 140.111633, "reward": "8,500円", "budget": "", "url": "https://www2.ms-r.com/MSR/MonitorNew/MyPage/EntryInput.asp?InvitationID=4178875"}, {"name": "新時代 宇都宮オリオン通り店", "address": "栃木県宇都宮市江野町10-1", "lat": 36.560234, "lng": 139.883179, "reward": "4,000円", "budget": "", "url": "https://www2.ms-r.com/MSR/MonitorNew/MyPage/EntryInput.asp?InvitationID=4269168"}, {"name": "新時代 群馬前橋店", "address": "群馬県前橋市千代田町5丁目1-4 アサカタクシービル2F", "lat": 36.390869, "lng": 139.071365, "reward": "4,000円", "budget": "", "url": "https://www2.ms-r.com/MSR/MonitorNew/MyPage/EntryInput.asp?InvitationID=4269224"}, {"name": "焼肉トラジ 高崎店", "address": "群馬県高崎市八島町46-1 高崎オーパ 8F", "lat": 36.323151, "lng": 139.011002, "reward": "8,500円", "budget": "", "url": "https://www2.ms-r.com/MSR/MonitorNew/MyPage/EntryInput.asp?InvitationID=4178880"}, {"name": "新時代 高崎駅前店", "address": "群馬県高崎市連雀町134 サファリビル1階", "lat": 36.324104, "lng": 139.006805, "reward": "4,000円", "budget": "", "url": "https://www2.ms-r.com/MSR/MonitorNew/MyPage/EntryInput.asp?InvitationID=4269187"}, {"name": "新時代 高崎駅東口店", "address": "群馬県高崎市栄町14-1 高崎イースト・センタービル1F", "lat": 36.321991, "lng": 139.014694, "reward": "4,000円", "budget": "", "url": "https://www2.ms-r.com/MSR/MonitorNew/MyPage/EntryInput.asp?InvitationID=4269202"}, {"name": "新時代 群馬太田駅南口店", "address": "群馬県太田市飯田町1387 山田ビル1F", "lat": 36.293083, "lng": 139.378723, "reward": "4,000円", "budget": "", "url": "https://www2.ms-r.com/MSR/MonitorNew/MyPage/EntryInput.asp?InvitationID=4269208"}, {"name": "焼肉トラジ コクーンシティ店", "address": "埼玉県さいたま市大宮区吉敷町４丁目２６７−２ コクーンシティ コクーン1 北館 ２階", "lat": 35.894691, "lng": 139.635742, "reward": "8,500円", "budget": "", "url": "https://www2.ms-r.com/MSR/MonitorNew/MyPage/EntryInput.asp?InvitationID=4178859"}, {"name": "新時代 さいたま新都心駅東口店", "address": "埼玉県さいたま市大宮区吉敷町4丁目59−1 新都心 Sﾋﾞﾙ1階", "lat": 35.895111, "lng": 139.63324, "reward": "4,000円", "budget": "", "url": "https://www2.ms-r.com/MSR/MonitorNew/MyPage/EntryInput.asp?InvitationID=4269176"}, {"name": "新時代 大宮駅南銀座通り店", "address": "埼玉県さいたま市大宮区仲町1丁目15 VORT大宮1F", "lat": 35.905243, "lng": 139.625427, "reward": "4,000円", "budget": "", "url": "https://www2.ms-r.com/MSR/MonitorNew/MyPage/EntryInput.asp?InvitationID=4269196"}, {"name": "新時代 川越クレアモールはなれ店", "address": "埼玉県川越市新富町2丁目13-1", "lat": 35.911232, "lng": 139.482254, "reward": "4,000円", "budget": "", "url": "https://www2.ms-r.com/MSR/MonitorNew/MyPage/EntryInput.asp?InvitationID=4269194"}, {"name": "新時代 川越西口店", "address": "埼玉県川越市脇田本町16-26 ｼﾏﾀﾞﾋﾞﾙ 1F･2F", "lat": 35.908279, "lng": 139.481476, "reward": "4,000円", "budget": "", "url": "https://www2.ms-r.com/MSR/MonitorNew/MyPage/EntryInput.asp?InvitationID=4269169"}, {"name": "新時代 川越クレアモール", "address": "埼玉県川越市新富町2-1-5", "lat": 35.913658, "lng": 139.482727, "reward": "4,000円", "budget": "", "url": "https://www2.ms-r.com/MSR/MonitorNew/MyPage/EntryInput.asp?InvitationID=4269170"}, {"name": "新時代 埼玉新所沢駅前店", "address": "埼玉県所沢市松葉町11-2 ユタカビル1F", "lat": 35.807388, "lng": 139.45639, "reward": "4,000円", "budget": "", "url": "https://www2.ms-r.com/MSR/MonitorNew/MyPage/EntryInput.asp?InvitationID=4269235"}, {"name": "新時代 志木駅東口", "address": "埼玉県志木市本町5丁目21-21 ウエストウッドビル1F", "lat": 35.824024, "lng": 139.574875, "reward": "4,000円", "budget": "", "url": "https://www2.ms-r.com/MSR/MonitorNew/MyPage/EntryInput.asp?InvitationID=4269217"}, {"name": "本千葉駅前の串屋横丁", "address": "千葉県千葉市中央区長洲1-23-4　長谷川ﾋﾞﾙ1F", "lat": 35.602665, "lng": 140.12149, "reward": "2,000円", "budget": "", "url": "https://www2.ms-r.com/MSR/MonitorNew/MyPage/EntryInput.asp?InvitationID=4232883"}, {"name": "もぢょい有限会社 蘇我駅西口店", "address": "千葉県千葉市中央区今井2-50-2　", "lat": 35.580696, "lng": 140.129135, "reward": "2,000円", "budget": "", "url": "https://www2.ms-r.com/MSR/MonitorNew/MyPage/EntryInput.asp?InvitationID=4232887"}, {"name": "焼肉トラジ 千葉店", "address": "千葉県千葉市中央区新千葉１丁目１−１ ペリエ千葉 ５Ｆ", "lat": 35.612953, "lng": 140.114136, "reward": "8,500円", "budget": "", "url": "https://www2.ms-r.com/MSR/MonitorNew/MyPage/EntryInput.asp?InvitationID=4178834"}, {"name": "もぢょい有限会社 幕張本郷店", "address": "千葉県千葉市花見川区幕張本郷6-26-15　TOZOビル　1F", "lat": 35.673771, "lng": 140.04393, "reward": "2,000円", "budget": "", "url": "https://www2.ms-r.com/MSR/MonitorNew/MyPage/EntryInput.asp?InvitationID=4232885"}, {"name": "稲毛海岸北口の串屋横丁", "address": "千葉県千葉市美浜区高州1-22-22江尻ビル　2Ｆ", "lat": 35.629486, "lng": 140.078568, "reward": "2,000円", "budget": "", "url": "https://www2.ms-r.com/MSR/MonitorNew/MyPage/EntryInput.asp?InvitationID=4232884"}, {"name": "焼肉トラジ イオンモール幕張新都心店", "address": "千葉県千葉市美浜区豊砂１−１ イオンモール ２Ｆ グランドモール", "lat": 35.65609, "lng": 140.02652, "reward": "8,500円", "budget": "", "url": "https://www2.ms-r.com/MSR/MonitorNew/MyPage/EntryInput.asp?InvitationID=4178833"}, {"name": "吉野家 都営線本八幡", "address": "千葉県市川市八幡２丁目１６－１４", "lat": 35.721844, "lng": 139.926025, "reward": "500円", "budget": "", "url": "https://www2.ms-r.com/MSR/MonitorNew/MyPage/EntryInput.asp?InvitationID=4348559"}, {"name": "新時代 船橋駅前店", "address": "千葉県船橋市本町4-5-27", "lat": 35.701366, "lng": 139.986984, "reward": "4,000円", "budget": "", "url": "https://www2.ms-r.com/MSR/MonitorNew/MyPage/EntryInput.asp?InvitationID=4269174"}, {"name": "焼肉トラジ アトレ松戸店", "address": "千葉県松戸市松戸１１８１ アトレ松戸7F", "lat": 35.783401, "lng": 139.900055, "reward": "8,500円", "budget": "", "url": "https://www2.ms-r.com/MSR/MonitorNew/MyPage/EntryInput.asp?InvitationID=4178876"}, {"name": "串焼屋 鶏ごっち 成田店", "address": "千葉県成田市花崎町533-15", "lat": 35.777859, "lng": 140.315765, "reward": "5,500円", "budget": "", "url": "https://www2.ms-r.com/MSR/MonitorNew/MyPage/EntryInput.asp?InvitationID=4339576"}, {"name": "焼肉トラジ アリオ柏店", "address": "千葉県柏市大島田１丁目６−１ セブンパークアリオ柏 ウェスト・ウィング 3F", "lat": 35.833759, "lng": 140.011703, "reward": "8,500円", "budget": "", "url": "https://www2.ms-r.com/MSR/MonitorNew/MyPage/EntryInput.asp?InvitationID=4178877"}, {"name": "焼肉トラジ 柏髙島屋ステーションモール店", "address": "千葉県柏市末広町１−１ S館 柏高島屋ステーションモール 専門店７Ｆ", "lat": 35.862377, "lng": 139.970825, "reward": "8,500円", "budget": "", "url": "https://www2.ms-r.com/MSR/MonitorNew/MyPage/EntryInput.asp?InvitationID=4178835"}, {"name": "もぢょい有限会社 八幡宿駅西口店", "address": "千葉県市原市八幡字808", "lat": 35.536446, "lng": 140.119934, "reward": "2,000円", "budget": "", "url": "https://www2.ms-r.com/MSR/MonitorNew/MyPage/EntryInput.asp?InvitationID=4232886"}, {"name": "新時代 流山おおたかの森", "address": "千葉県流山市おおたかの森西1-2-2", "lat": 35.87191, "lng": 139.924286, "reward": "4,000円", "budget": "", "url": "https://www2.ms-r.com/MSR/MonitorNew/MyPage/EntryInput.asp?InvitationID=4269171"}, {"name": "焼肉トラジ イクスピアリ店", "address": "千葉県浦安市舞浜１−４ イクスピアリ ３Ｆ", "lat": 35.631268, "lng": 139.874329, "reward": "8,500円", "budget": "", "url": "https://www2.ms-r.com/MSR/MonitorNew/MyPage/EntryInput.asp?InvitationID=4178832"}, {"name": "すし銚子丸 横芝店", "address": "千葉県山武郡横芝光町横芝2157-1", "lat": 35.659779, "lng": 140.484283, "reward": "2,500円", "budget": "", "url": "https://www2.ms-r.com/MSR/MonitorNew/MyPage/EntryInput.asp?InvitationID=4328647"}, {"name": "とり鉄 秋葉原昭和通り店", "address": "東京都千代田区神田佐久間町1-18　", "lat": 35.6978, "lng": 139.774399, "reward": "4,500円", "budget": "", "url": "https://www2.ms-r.com/MSR/MonitorNew/MyPage/EntryInput.asp?InvitationID=4264431"}, {"name": "肉匠の牛たん たん之助酒場 大手町店", "address": "東京都千代田区大手町1-1-1 大手町パークビルディング B1F", "lat": 35.685982, "lng": 139.762329, "reward": "5,000円", "budget": "", "url": "https://www2.ms-r.com/MSR/MonitorNew/MyPage/EntryInput.asp?InvitationID=4177044"}, {"name": "牛たん酒場 たん之助 丸の内オアゾ店", "address": "東京都千代田区丸の内1-6-4　丸の内オアゾ5F", "lat": 35.683708, "lng": 139.766266, "reward": "5,000円", "budget": "", "url": "https://www2.ms-r.com/MSR/MonitorNew/MyPage/EntryInput.asp?InvitationID=4177047"}, {"name": "たん之助 ヨドバシAkiba店", "address": "東京都千代田区神田花岡町1- 1ヨドバシAkiba 8F", "lat": 35.698639, "lng": 139.774612, "reward": "4,500円", "budget": "", "url": "https://www2.ms-r.com/MSR/MonitorNew/MyPage/EntryInput.asp?InvitationID=4177056"}, {"name": "焼肉トラジ 丸ビル店", "address": "東京都千代田区丸の内２丁目４−１ 丸の内ビルディング ６Ｆ", "lat": 35.681046, "lng": 139.763794, "reward": "8,500円", "budget": "", "url": "https://www2.ms-r.com/MSR/MonitorNew/MyPage/EntryInput.asp?InvitationID=4178825"}, {"name": "焼肉トラジ 秋葉原店", "address": "東京都千代田区神田佐久間町１丁目６−５ アキバ・トリム ５Ｆ", "lat": 35.697826, "lng": 139.773346, "reward": "8,500円", "budget": "", "url": "https://www2.ms-r.com/MSR/MonitorNew/MyPage/EntryInput.asp?InvitationID=4178829"}, {"name": "焼肉トラジ 神田店", "address": "東京都千代田区内神田３丁目１２−１０ 神田西口NSビル ３Ｆ", "lat": 35.691242, "lng": 139.770279, "reward": "8,500円", "budget": "", "url": "https://www2.ms-r.com/MSR/MonitorNew/MyPage/EntryInput.asp?InvitationID=4178827"}, {"name": "焼肉トラジ トレーニングセンター店", "address": "東京都千代田区丸の内３丁目７−１７", "lat": 35.677288, "lng": 139.765182, "reward": "8,500円", "budget": "", "url": "https://www2.ms-r.com/MSR/MonitorNew/MyPage/EntryInput.asp?InvitationID=4178864"}, {"name": "焼肉トラジ 日比谷店", "address": "東京都千代田区有楽町１丁目５−２ 東宝日比谷プロムナードビル B２F", "lat": 35.674419, "lng": 139.759888, "reward": "8,500円", "budget": "", "url": "https://www2.ms-r.com/MSR/MonitorNew/MyPage/EntryInput.asp?InvitationID=4178865"}, {"name": "新時代 有楽町店", "address": "東京都千代田区丸の内3丁目6-18", "lat": 35.676189, "lng": 139.764404, "reward": "4,000円", "budget": "", "url": "https://www2.ms-r.com/MSR/MonitorNew/MyPage/EntryInput.asp?InvitationID=4269116"}, {"name": "魚の店 オカモ倶楽部 丸の内店", "address": "東京都千代田区丸の内2-7-3 東京ビル TOKIA B1F", "lat": 35.679085, "lng": 139.764679, "reward": "5,000円", "budget": "", "url": "https://www2.ms-r.com/MSR/MonitorNew/MyPage/EntryInput.asp?InvitationID=4325225"}, {"name": "NISSAN CROSSING CAFE", "address": "東京都中央区銀座5-8-1 銀座プレイス NISSAN CROSSING内 2階", "lat": 35.670975, "lng": 139.76503, "reward": "1,500円", "budget": "", "url": "https://www2.ms-r.com/MSR/MonitorNew/MyPage/EntryInput.asp?InvitationID=4310926"}, {"name": "焼肉トラジ 京橋店", "address": "東京都中央区京橋３丁目１−１ 東京スクエアガーデン ２階", "lat": 35.676559, "lng": 139.768524, "reward": "8,500円", "budget": "", "url": "https://www2.ms-r.com/MSR/MonitorNew/MyPage/EntryInput.asp?InvitationID=4178826"}, {"name": "焼肉トラジ 銀座8丁目店", "address": "東京都中央区銀座８丁目３−１０ トミタビル ２Ｆ", "lat": 35.668934, "lng": 139.758972, "reward": "8,500円", "budget": "", "url": "https://www2.ms-r.com/MSR/MonitorNew/MyPage/EntryInput.asp?InvitationID=4178850"}, {"name": "焼肉トラジ 銀座6丁目店", "address": "東京都中央区銀座６丁目３−１１ 西銀座ビル 4F", "lat": 35.671116, "lng": 139.760849, "reward": "8,500円", "budget": "", "url": "https://www2.ms-r.com/MSR/MonitorNew/MyPage/EntryInput.asp?InvitationID=4178851"}, {"name": "焼肉トラジ 晴海トリトン店", "address": "東京都中央区晴海１丁目８−１６ トリトン ３Ｆ", "lat": 35.655556, "lng": 139.78183, "reward": "8,500円", "budget": "", "url": "https://www2.ms-r.com/MSR/MonitorNew/MyPage/EntryInput.asp?InvitationID=4178872"}, {"name": "焼肉ビストロ　牛印 京橋エドグラン店", "address": "東京都中央区京橋2-2-1京橋エドグランB1F", "lat": 35.677818, "lng": 139.769318, "reward": "14,000円", "budget": "", "url": "https://www2.ms-r.com/MSR/MonitorNew/MyPage/EntryInput.asp?InvitationID=4347375"}, {"name": "焼肉　牛印 銀座8丁目店", "address": "東京都中央区銀座8-3-10　トミタビルB1F", "lat": 35.668934, "lng": 139.758972, "reward": "24,500円", "budget": "", "url": "https://www2.ms-r.com/MSR/MonitorNew/MyPage/EntryInput.asp?InvitationID=4347376"}, {"name": "Little Darling COFFEE ROASTERS", "address": "東京都港区南青山1-12-32", "lat": 35.668617, "lng": 139.724838, "reward": "1,500円", "budget": "", "url": "https://www2.ms-r.com/MSR/MonitorNew/MyPage/EntryInput.asp?InvitationID=4310907"}, {"name": "牛たん酒場 たん之助 msb田町店", "address": "東京都港区芝浦3-1-21 msb Tamachi　田町ステーションタワーN 1F", "lat": 35.644985, "lng": 139.748886, "reward": "5,000円", "budget": "", "url": "https://www2.ms-r.com/MSR/MonitorNew/MyPage/EntryInput.asp?InvitationID=4177045"}, {"name": "焼肉トラジ 新橋店", "address": "東京都港区新橋１丁目１５−５ １１５ １１Ｆ・１２Ｆ", "lat": 35.668022, "lng": 139.757233, "reward": "8,500円", "budget": "", "url": "https://www2.ms-r.com/MSR/MonitorNew/MyPage/EntryInput.asp?InvitationID=4178847"}, {"name": "焼肉トラジ PARAM カレッタ汐留店", "address": "東京都港区東新橋１丁目８−１ カレッタ汐留 ４６Ｆ", "lat": 35.664555, "lng": 139.762268, "reward": "8,500円", "budget": "", "url": "https://www2.ms-r.com/MSR/MonitorNew/MyPage/EntryInput.asp?InvitationID=4178874"}, {"name": "焼肉トラジ 田町店", "address": "東京都港区芝浦３丁目１−２１ Msb Tamachi 田町ステーションタワーS ２F", "lat": 35.644985, "lng": 139.748886, "reward": "8,500円", "budget": "", "url": "https://www2.ms-r.com/MSR/MonitorNew/MyPage/EntryInput.asp?InvitationID=4178863"}, {"name": "焼肉トラジ 麻布十番店", "address": "東京都港区麻布十番１丁目１０−３ モンテプラザ麻布 ２Ｆ", "lat": 35.656143, "lng": 139.736618, "reward": "8,500円", "budget": "", "url": "https://www2.ms-r.com/MSR/MonitorNew/MyPage/EntryInput.asp?InvitationID=4178866"}, {"name": "焼肉トラジ 青山店", "address": "東京都港区北青山３丁目５−１７ ストラーダビル Ｂ１Ｆ", "lat": 35.665634, "lng": 139.712769, "reward": "8,500円", "budget": "", "url": "https://www2.ms-r.com/MSR/MonitorNew/MyPage/EntryInput.asp?InvitationID=4178867"}, {"name": "焼肉　牛印 西麻布店", "address": "東京都港区西麻布2-13-15", "lat": 35.660912, "lng": 139.722794, "reward": "31,000円", "budget": "", "url": "https://www2.ms-r.com/MSR/MonitorNew/MyPage/EntryInput.asp?InvitationID=4347378"}, {"name": "新時代 田町三田店", "address": "東京都港区芝5丁目21-14", "lat": 35.648331, "lng": 139.747131, "reward": "4,000円", "budget": "", "url": "https://www2.ms-r.com/MSR/MonitorNew/MyPage/EntryInput.asp?InvitationID=4269233"}, {"name": "新時代 新宿西口店", "address": "東京都新宿区西新宿1-15-3", "lat": 35.688992, "lng": 139.697525, "reward": "4,000円", "budget": "", "url": "https://www2.ms-r.com/MSR/MonitorNew/MyPage/EntryInput.asp?InvitationID=4269154"}, {"name": "新時代 新宿西口大ガード店", "address": "東京都新宿区西新宿1-3-1 サンフラワービル2F", "lat": 35.69339, "lng": 139.698929, "reward": "4,000円", "budget": "", "url": "https://www2.ms-r.com/MSR/MonitorNew/MyPage/EntryInput.asp?InvitationID=4269186"}, {"name": "焼肉　牛印 神楽坂店", "address": "東京都新宿区神楽坂3-6-3　ヒルトップビル1階", "lat": 35.701012, "lng": 139.739624, "reward": "24,500円", "budget": "", "url": "https://www2.ms-r.com/MSR/MonitorNew/MyPage/EntryInput.asp?InvitationID=4347377"}, {"name": "焼肉トラジ 新宿西口店", "address": "東京都新宿区西新宿7-2-5 TH西新宿ビル3F", "lat": 35.695229, "lng": 139.698639, "reward": "8,500円", "budget": "", "url": "https://www2.ms-r.com/MSR/MonitorNew/MyPage/EntryInput.asp?InvitationID=4178879"}, {"name": "焼肉トラジ 新宿店", "address": "東京都新宿区歌舞伎町1-2-6　三経55ビル2〜3F", "lat": 35.693951, "lng": 139.703934, "reward": "8,500円", "budget": "", "url": "https://www2.ms-r.com/MSR/MonitorNew/MyPage/EntryInput.asp?InvitationID=4178854"}, {"name": "焼肉トラジ 新宿東宝ビル店", "address": "東京都新宿区歌舞伎町１丁目１９−１ 新宿東宝ビル １Ｆ", "lat": 35.694897, "lng": 139.702133, "reward": "8,500円", "budget": "", "url": "https://www2.ms-r.com/MSR/MonitorNew/MyPage/EntryInput.asp?InvitationID=4178855"}, {"name": "牛たん酒場 たん之助 COMORE四谷店", "address": "東京都新宿区四谷1-6-1 COMORE Mall 1F", "lat": 35.687668, "lng": 139.72905, "reward": "5,000円", "budget": "", "url": "https://www2.ms-r.com/MSR/MonitorNew/MyPage/EntryInput.asp?InvitationID=4177046"}, {"name": "魚の店 オカモ倶楽部 新宿店", "address": "東京都新宿区新宿３丁目３１−５", "lat": 35.690632, "lng": 139.70369, "reward": "5,000円", "budget": "", "url": "https://www2.ms-r.com/MSR/MonitorNew/MyPage/EntryInput.asp?InvitationID=4325226"}, {"name": "新時代 上野店", "address": "東京都台東区上野六丁目13番5号 上野エイトビル地下1階", "lat": 35.710655, "lng": 139.775024, "reward": "4,000円", "budget": "", "url": "https://www2.ms-r.com/MSR/MonitorNew/MyPage/EntryInput.asp?InvitationID=4269191"}, {"name": "焼肉トラジ 上野店", "address": "東京都台東区上野２丁目１４−３１ レイクサイドビル ５Ｆ", "lat": 35.710613, "lng": 139.773239, "reward": "8,500円", "budget": "", "url": "https://www2.ms-r.com/MSR/MonitorNew/MyPage/EntryInput.asp?InvitationID=4178828"}, {"name": "SKYTREE CAFE(350)", "address": "東京都墨田区押上1-1-2 東京ソラマチ 東京スカイツリー天望デッキ フロア350", "lat": 35.710083, "lng": 139.808609, "reward": "1,500円", "budget": "", "url": "https://www2.ms-r.com/MSR/MonitorNew/MyPage/EntryInput.asp?InvitationID=4310924"}, {"name": "焼肉トラジ 錦糸町店", "address": "東京都墨田区江東橋３丁目１４−５ ＴＥＲＭＩＮＡ５Ｆ", "lat": 35.696247, "lng": 139.814499, "reward": "8,500円", "budget": "", "url": "https://www2.ms-r.com/MSR/MonitorNew/MyPage/EntryInput.asp?InvitationID=4178830"}, {"name": "新時代 錦糸町南口店", "address": "東京都墨田区江東橋3-12-3 錦糸町Artemis Keiyo1階", "lat": 35.696022, "lng": 139.813202, "reward": "4,000円", "budget": "", "url": "https://www2.ms-r.com/MSR/MonitorNew/MyPage/EntryInput.asp?InvitationID=4269145"}, {"name": "焼肉トラジ 豊洲店", "address": "東京都江東区豊洲３丁目２−２４ 豊洲フォレシア 1F 豊洲フォレシア 1F", "lat": 35.656982, "lng": 139.794495, "reward": "8,500円", "budget": "", "url": "https://www2.ms-r.com/MSR/MonitorNew/MyPage/EntryInput.asp?InvitationID=4178871"}, {"name": "美食焼肉トラジ 葉菜 SUNAMO店", "address": "東京都江東区新砂3-4-31南砂町ショッピングセンターSUNAMO 4F", "lat": 35.665485, "lng": 139.834488, "reward": "5,500円", "budget": "", "url": "https://www2.ms-r.com/MSR/MonitorNew/MyPage/EntryInput.asp?InvitationID=4177053"}, {"name": "牛たん酒場 たん之助 豊洲店", "address": "東京都江東区豊洲2-1-9 豊洲セイルパーク2F", "lat": 35.656776, "lng": 139.793976, "reward": "5,000円", "budget": "", "url": "https://www2.ms-r.com/MSR/MonitorNew/MyPage/EntryInput.asp?InvitationID=4177048"}, {"name": "新時代 五反田西口店", "address": "東京都品川区⻄五反田 1-4-4 ﾀﾃｲｼﾋﾞﾙ 2 階", "lat": 35.608997, "lng": 139.730225, "reward": "4,000円", "budget": "", "url": "https://www2.ms-r.com/MSR/MonitorNew/MyPage/EntryInput.asp?InvitationID=4269166"}, {"name": "タイ食堂 くるみ", "address": "東京都品川区上大崎2-26-5 メグロードビル B1F", "lat": 35.633987, "lng": 139.7146, "reward": "5,500円", "budget": "", "url": "https://www2.ms-r.com/MSR/MonitorNew/MyPage/EntryInput.asp?InvitationID=4297248"}, {"name": "焼肉 冷麺　ういしろ", "address": "東京都品川区西五反田2-29-10 五反田サニーフラット 103", "lat": 35.624474, "lng": 139.720383, "reward": "10,000円", "budget": "", "url": "https://www2.ms-r.com/MSR/MonitorNew/MyPage/EntryInput.asp?InvitationID=4325231"}, {"name": "焼肉トラジ 自由が丘店", "address": "東京都目黒区自由が丘1-26-14 オクズミビル2F", "lat": 35.609249, "lng": 139.668365, "reward": "8,500円", "budget": "", "url": "https://www2.ms-r.com/MSR/MonitorNew/MyPage/EntryInput.asp?InvitationID=4178882"}, {"name": "はんろく", "address": "東京都目黒区平町1-25-16 クサムラコーポ 1F 奥", "lat": 35.616898, "lng": 139.676682, "reward": "5,000円", "budget": "", "url": "https://www2.ms-r.com/MSR/MonitorNew/MyPage/EntryInput.asp?InvitationID=4221358"}, {"name": "魚の店 オカモ倶楽部", "address": "東京都目黒区上目黒３丁目５-２９ 中目黒高架下Ｆ１区画", "lat": 35.643215, "lng": 139.697601, "reward": "5,000円", "budget": "", "url": "https://www2.ms-r.com/MSR/MonitorNew/MyPage/EntryInput.asp?InvitationID=4325224"}, {"name": "とり鉄 明大前駅前店", "address": "東京都世田谷区松原1-38-4　第56東京ビルB1F", "lat": 35.668736, "lng": 139.650772, "reward": "4,500円", "budget": "", "url": "https://www2.ms-r.com/MSR/MonitorNew/MyPage/EntryInput.asp?InvitationID=4264453"}, {"name": "とり鉄 三軒茶屋店", "address": "東京都世田谷区三軒茶屋1-38-7　フォーラムN&NB1F", "lat": 35.643414, "lng": 139.67131, "reward": "4,500円", "budget": "", "url": "https://www2.ms-r.com/MSR/MonitorNew/MyPage/EntryInput.asp?InvitationID=4264447"}, {"name": "新時代 三軒茶屋店", "address": "東京都世田谷区太子堂４-1-1 キャロットタワー北棟２F", "lat": 35.643543, "lng": 139.66983, "reward": "4,000円", "budget": "", "url": "https://www2.ms-r.com/MSR/MonitorNew/MyPage/EntryInput.asp?InvitationID=4269115"}, {"name": "焼肉トラジ 玉川高島屋S･C店", "address": "東京都世田谷区玉川３丁目１７−１８ 南館 ９Ｆ 高島屋Ｓ・Ｃ店 新南館9F", "lat": 35.614872, "lng": 139.626816, "reward": "8,500円", "budget": "", "url": "https://www2.ms-r.com/MSR/MonitorNew/MyPage/EntryInput.asp?InvitationID=4178868"}, {"name": "酒場シナトラ 自由が丘店", "address": "東京都世田谷区奥沢5-42-3　トレインチ自由が丘", "lat": 35.606308, "lng": 139.666794, "reward": "5,500円", "budget": "", "url": "https://www2.ms-r.com/MSR/MonitorNew/MyPage/EntryInput.asp?InvitationID=4297234"}, {"name": "焼肉ここから 渋谷道玄坂店", "address": "東京都渋谷区道玄坂2-18-11 サンモール道玄坂106", "lat": 35.659042, "lng": 139.696045, "reward": "7,500円", "budget": "", "url": "https://www2.ms-r.com/MSR/MonitorNew/MyPage/EntryInput.asp?InvitationID=4232233"}, {"name": "焼肉トラジ 恵比寿庵店", "address": "東京都渋谷区恵比寿南１丁目１−１０", "lat": 35.646557, "lng": 139.708389, "reward": "8,500円", "budget": "", "url": "https://www2.ms-r.com/MSR/MonitorNew/MyPage/EntryInput.asp?InvitationID=4178862"}, {"name": "焼肉トラジ 恵比寿園店", "address": "東京都渋谷区恵比寿１丁目６−９", "lat": 35.648033, "lng": 139.710953, "reward": "8,500円", "budget": "", "url": "https://www2.ms-r.com/MSR/MonitorNew/MyPage/EntryInput.asp?InvitationID=4178861"}, {"name": "焼肉トラジ 本店", "address": "東京都渋谷区恵比寿南２丁目２−４ 山燃２ビル １，２Ｆ", "lat": 35.645706, "lng": 139.707367, "reward": "8,500円", "budget": "", "url": "https://www2.ms-r.com/MSR/MonitorNew/MyPage/EntryInput.asp?InvitationID=4178860"}, {"name": "焼肉トラジ 新宿タカシマヤ店", "address": "東京都渋谷区千駄ケ谷５丁目２４−２ タイムズスクエアビル １４Ｆ", "lat": 35.684647, "lng": 139.703354, "reward": "8,500円", "budget": "", "url": "https://www2.ms-r.com/MSR/MonitorNew/MyPage/EntryInput.asp?InvitationID=4178856"}, {"name": "焼肉レストラン まちや", "address": "東京都渋谷区恵比寿南2-1-2 ＲＫＦ恵比寿 1Ｆ", "lat": 35.645893, "lng": 139.707306, "reward": "13,500円", "budget": "", "url": "https://www2.ms-r.com/MSR/MonitorNew/MyPage/EntryInput.asp?InvitationID=4325235"}, {"name": "お料理 五勝手", "address": "東京都渋谷区猿楽町2-13 F93Daikanyama", "lat": 35.653446, "lng": 139.704712, "reward": "8,500円", "budget": "", "url": "https://www2.ms-r.com/MSR/MonitorNew/MyPage/EntryInput.asp?InvitationID=4325232"}, {"name": "肉汁餃子のダンダダン 阿佐ヶ谷店", "address": "東京都杉並区阿佐ヶ谷北2-13-19　三宅店舗", "lat": 35.7062, "lng": 139.636124, "reward": "3,000円", "budget": "", "url": "https://www2.ms-r.com/MSR/MonitorNew/MyPage/EntryInput.asp?InvitationID=4308686"}, {"name": "新時代 高円寺北口店", "address": "東京都杉並区高円寺北3-22-11", "lat": 35.706284, "lng": 139.649216, "reward": "4,000円", "budget": "", "url": "https://www2.ms-r.com/MSR/MonitorNew/MyPage/EntryInput.asp?InvitationID=4269162"}, {"name": "焼肉トラジ 池袋西口店", "address": "東京都豊島区西池袋1-17-7　ルミエールビル6F", "lat": 35.731178, "lng": 139.708389, "reward": "8,500円", "budget": "", "url": "https://www2.ms-r.com/MSR/MonitorNew/MyPage/EntryInput.asp?InvitationID=4178878"}, {"name": "新時代 池袋サンシャイン６０通り店", "address": "東京都豊島区東池袋1丁目29−1 ﾏﾙﾋﾞﾙ", "lat": 35.730293, "lng": 139.716522, "reward": "4,000円", "budget": "", "url": "https://www2.ms-r.com/MSR/MonitorNew/MyPage/EntryInput.asp?InvitationID=4269175"}, {"name": "焼肉トラジ 池袋東口店", "address": "東京都豊島区南池袋２丁目２７−５ 共和ビル Ｂ１Ｆ", "lat": 35.728378, "lng": 139.713516, "reward": "8,500円", "budget": "", "url": "https://www2.ms-r.com/MSR/MonitorNew/MyPage/EntryInput.asp?InvitationID=4178858"}, {"name": "焼肉トラジ サンシャイン店", "address": "東京都豊島区東池袋３丁目１ サンシャインシティ専門店街アルパ ３Ｆ", "lat": 35.72929, "lng": 139.719193, "reward": "8,500円", "budget": "", "url": "https://www2.ms-r.com/MSR/MonitorNew/MyPage/EntryInput.asp?InvitationID=4178857"}, {"name": "魚屋 みらく劇場", "address": "東京都豊島区北大塚2-28-7", "lat": 35.732967, "lng": 139.729736, "reward": "4,000円", "budget": "", "url": "https://www2.ms-r.com/MSR/MonitorNew/MyPage/EntryInput.asp?InvitationID=4325222"}, {"name": "新時代 赤羽本店", "address": "東京都北区赤羽1丁目23-2 亀谷ビル2F", "lat": 35.779705, "lng": 139.721191, "reward": "4,000円", "budget": "", "url": "https://www2.ms-r.com/MSR/MonitorNew/MyPage/EntryInput.asp?InvitationID=4269243"}, {"name": "焼肉トラジ 北千住店", "address": "東京都足立区千住３丁目７７ きた テラス ３Ｆ", "lat": 35.751637, "lng": 139.802704, "reward": "8,500円", "budget": "", "url": "https://www2.ms-r.com/MSR/MonitorNew/MyPage/EntryInput.asp?InvitationID=4178831"}, {"name": "新時代 北千住駅西口店", "address": "東京都足立区千住2丁目61 びっくりや北千住西口ビル５F", "lat": 35.749725, "lng": 139.80397, "reward": "4,000円", "budget": "", "url": "https://www2.ms-r.com/MSR/MonitorNew/MyPage/EntryInput.asp?InvitationID=4269242"}, {"name": "神戸元町ドリア 神戸元町ドリア　セレオ八王子店", "address": "東京都八王子市旭町1-1　10F", "lat": 35.655796, "lng": 139.336212, "reward": "1,000円", "budget": "", "url": "https://www2.ms-r.com/MSR/MonitorNew/MyPage/EntryInput.asp?InvitationID=4233605"}, {"name": "焼肉トラジ セレオ八王子店", "address": "東京都八王子市旭町１−１ セレオ八王子 １０Ｆ", "lat": 35.655796, "lng": 139.336212, "reward": "8,500円", "budget": "", "url": "https://www2.ms-r.com/MSR/MonitorNew/MyPage/EntryInput.asp?InvitationID=4178848"}, {"name": "新時代 吉祥寺南口店", "address": "東京都武蔵野市吉祥寺南町1-3-4 吉祥寺南口ﾋﾞﾙ2階", "lat": 35.702255, "lng": 139.579605, "reward": "4,000円", "budget": "", "url": "https://www2.ms-r.com/MSR/MonitorNew/MyPage/EntryInput.asp?InvitationID=4269117"}, {"name": "新時代 吉祥寺北口武蔵通り店", "address": "東京都武蔵野市吉祥寺本町1-2-8 真栄ビル2F", "lat": 35.703793, "lng": 139.578842, "reward": "4,000円", "budget": "", "url": "https://www2.ms-r.com/MSR/MonitorNew/MyPage/EntryInput.asp?InvitationID=4269184"}, {"name": "焼肉トラジ 吉祥寺店", "address": "東京都武蔵野市吉祥寺本町１丁目８−２１", "lat": 35.704525, "lng": 139.579819, "reward": "8,500円", "budget": "", "url": "https://www2.ms-r.com/MSR/MonitorNew/MyPage/EntryInput.asp?InvitationID=4178870"}, {"name": "焼肉トラジ トラジハイレーン南町田店", "address": "東京都町田市鶴間３丁目３−１ セントラルコート グランベリーパーク 2F", "lat": 35.511024, "lng": 139.47139, "reward": "8,500円", "budget": "", "url": "https://www2.ms-r.com/MSR/MonitorNew/MyPage/EntryInput.asp?InvitationID=4178852"}, {"name": "焼肉トラジ 町田店", "address": "東京都町田市原町田6-2-6　町田モディ 10F", "lat": 35.543522, "lng": 139.445145, "reward": "8,500円", "budget": "", "url": "https://www2.ms-r.com/MSR/MonitorNew/MyPage/EntryInput.asp?InvitationID=4178845"}, {"name": "たん之助 町田モディ店", "address": "東京都町田市原町田6-2-6町田モディ 9F", "lat": 35.543522, "lng": 139.445145, "reward": "4,500円", "budget": "", "url": "https://www2.ms-r.com/MSR/MonitorNew/MyPage/EntryInput.asp?InvitationID=4177055"}, {"name": "焼肉トラジ 国立店", "address": "東京都国分寺市日吉町３丁目２４−７", "lat": 35.704018, "lng": 139.454041, "reward": "8,500円", "budget": "", "url": "https://www2.ms-r.com/MSR/MonitorNew/MyPage/EntryInput.asp?InvitationID=4178846"}, {"name": "焼肉トラジ 鶴屋町店", "address": "神奈川県横浜市神奈川区鶴屋町２丁目１６−１０ エフテムＲＯＮビル３Ｆ", "lat": 35.468246, "lng": 139.62294, "reward": "8,500円", "budget": "", "url": "https://www2.ms-r.com/MSR/MonitorNew/MyPage/EntryInput.asp?InvitationID=4178840"}, {"name": "たん之助 ヨドバシ横浜店", "address": "神奈川県横浜市西区北幸1-2-7 ヨドバシ横浜 B2F", "lat": 35.467499, "lng": 139.620193, "reward": "4,500円", "budget": "", "url": "https://www2.ms-r.com/MSR/MonitorNew/MyPage/EntryInput.asp?InvitationID=4177054"}, {"name": "新時代 横浜駅西口店", "address": "神奈川県横浜市西区南幸2-10-15 ﾗｲｵﾝｽﾞﾏﾝｼｮﾝ横浜西口1F", "lat": 35.463123, "lng": 139.617325, "reward": "4,000円", "budget": "", "url": "https://www2.ms-r.com/MSR/MonitorNew/MyPage/EntryInput.asp?InvitationID=4269147"}, {"name": "新時代 横浜駅パルナード店", "address": "神奈川県横浜市西区南幸2-17-8横浜ﾄﾗｽﾄﾋﾞﾙ1F", "lat": 35.463661, "lng": 139.616089, "reward": "4,000円", "budget": "", "url": "https://www2.ms-r.com/MSR/MonitorNew/MyPage/EntryInput.asp?InvitationID=4269159"}, {"name": "新時代 横浜駅前", "address": "神奈川県横浜市西区南幸1-10-3 宮本ビルB1", "lat": 35.464973, "lng": 139.619843, "reward": "4,000円", "budget": "", "url": "https://www2.ms-r.com/MSR/MonitorNew/MyPage/EntryInput.asp?InvitationID=4269211"}, {"name": "新時代 横浜野毛店", "address": "神奈川県横浜市中区花咲町1丁目36", "lat": 35.449245, "lng": 139.630768, "reward": "4,000円", "budget": "", "url": "https://www2.ms-r.com/MSR/MonitorNew/MyPage/EntryInput.asp?InvitationID=4269231"}, {"name": "新時代 新横浜店", "address": "神奈川県横浜市港北区新横浜2-4-6 ﾏｽﾆ第一ﾋﾞﾙ", "lat": 35.508781, "lng": 139.616241, "reward": "4,000円", "budget": "", "url": "https://www2.ms-r.com/MSR/MonitorNew/MyPage/EntryInput.asp?InvitationID=4269135"}, {"name": "焼肉トラジ 新横浜店", "address": "神奈川県横浜市港北区新横浜２丁目１００−４５ キュービックプラザ新横浜 ９Ｆ", "lat": 35.508678, "lng": 139.614029, "reward": "8,500円", "budget": "", "url": "https://www2.ms-r.com/MSR/MonitorNew/MyPage/EntryInput.asp?InvitationID=4178841"}, {"name": "焼肉トラジ トレッサ横浜店", "address": "神奈川県横浜市港北区師岡町７００番地 トレッサ 横浜南棟 ２Ｆ", "lat": 35.524197, "lng": 139.645462, "reward": "8,500円", "budget": "", "url": "https://www2.ms-r.com/MSR/MonitorNew/MyPage/EntryInput.asp?InvitationID=4178842"}, {"name": "焼肉トラジ 上大岡店", "address": "神奈川県横浜市港南区上大岡西１丁目６−１ ウィング上大岡 B1F", "lat": 35.408283, "lng": 139.596436, "reward": "8,500円", "budget": "", "url": "https://www2.ms-r.com/MSR/MonitorNew/MyPage/EntryInput.asp?InvitationID=4178853"}, {"name": "焼肉トラジ たまプラーザテラス店", "address": "神奈川県横浜市青葉区美しが丘１丁目１−２ たまプラーザＴＥＲＲＡＣＥ ＧＡＴＥ ＰＬＡＺＡ３Ｆ", "lat": 35.578224, "lng": 139.559586, "reward": "8,500円", "budget": "", "url": "https://www2.ms-r.com/MSR/MonitorNew/MyPage/EntryInput.asp?InvitationID=4178869"}, {"name": "焼肉トラジ 京急川崎店", "address": "神奈川県川崎市川崎区砂子１丁目３−１ ウィングキッチン京急川崎 ３Ｆ", "lat": 35.532097, "lng": 139.700485, "reward": "8,500円", "budget": "", "url": "https://www2.ms-r.com/MSR/MonitorNew/MyPage/EntryInput.asp?InvitationID=4178844"}, {"name": "新時代 川崎仲見世通り店", "address": "神奈川県川崎市川崎区砂子2-2-5", "lat": 35.529366, "lng": 139.699524, "reward": "4,000円", "budget": "", "url": "https://www2.ms-r.com/MSR/MonitorNew/MyPage/EntryInput.asp?InvitationID=4269158"}, {"name": "新時代 溝の口店", "address": "神奈川県川崎市高津区溝口1丁目9-5 ｽｷﾞｻﾞｷﾋﾞﾙ1F", "lat": 35.599785, "lng": 139.611984, "reward": "4,000円", "budget": "", "url": "https://www2.ms-r.com/MSR/MonitorNew/MyPage/EntryInput.asp?InvitationID=4269149"}, {"name": "ビストロ BISTRO309 ららぽーと湘南平塚店", "address": "神奈川県平塚市天沼１０－１", "lat": 35.33651, "lng": 139.352646, "reward": "1,000円", "budget": "", "url": "https://www2.ms-r.com/MSR/MonitorNew/MyPage/EntryInput.asp?InvitationID=4225162"}, {"name": "快 平塚豊田店", "address": "神奈川県平塚市南豊田55-1", "lat": 35.356274, "lng": 139.326706, "reward": "4,500円", "budget": "", "url": "https://www2.ms-r.com/MSR/MonitorNew/MyPage/EntryInput.asp?InvitationID=4176862"}, {"name": "麦酒宿ランドリー", "address": "神奈川県藤沢市鵠沼橘1-17-2　鵠沼橘店舗1階", "lat": 35.337048, "lng": 139.486496, "reward": "4,000円", "budget": "", "url": "https://www2.ms-r.com/MSR/MonitorNew/MyPage/EntryInput.asp?InvitationID=4277580"}, {"name": "新時代 神奈川小田原駅前店", "address": "神奈川県小田原市栄町1丁目2-10", "lat": 35.255127, "lng": 139.157333, "reward": "4,000円", "budget": "", "url": "https://www2.ms-r.com/MSR/MonitorNew/MyPage/EntryInput.asp?InvitationID=4269232"}, {"name": "快 小田原駅前店", "address": "神奈川県小田原市栄町2-7-2　", "lat": 35.25552, "lng": 139.157684, "reward": "4,500円", "budget": "", "url": "https://www2.ms-r.com/MSR/MonitorNew/MyPage/EntryInput.asp?InvitationID=4176861"}, {"name": "やきとりの快 小田原駅前店", "address": "神奈川県小田原市栄町1-4-3 山崎ビル1F", "lat": 35.254475, "lng": 139.155838, "reward": "4,500円", "budget": "", "url": "https://www2.ms-r.com/MSR/MonitorNew/MyPage/EntryInput.asp?InvitationID=4176866"}, {"name": "快 小田原店", "address": "神奈川県小田原市下大井433-4", "lat": 35.313194, "lng": 139.161514, "reward": "4,500円", "budget": "", "url": "https://www2.ms-r.com/MSR/MonitorNew/MyPage/EntryInput.asp?InvitationID=4176863"}, {"name": "ふじ丸 本店", "address": "神奈川県小田原市下大井472", "lat": 35.31419, "lng": 139.161194, "reward": "4,000円", "budget": "", "url": "https://www2.ms-r.com/MSR/MonitorNew/MyPage/EntryInput.asp?InvitationID=4176899"}, {"name": "新時代 小田急マルシェ秦野店", "address": "神奈川県秦野市大秦町1-1 小田急マルシェ2階", "lat": 35.370495, "lng": 139.226273, "reward": "4,000円", "budget": "", "url": "https://www2.ms-r.com/MSR/MonitorNew/MyPage/EntryInput.asp?InvitationID=4300636"}, {"name": "新時代 神奈川本厚木駅前店", "address": "神奈川県厚木市中町3-1-24 吉村ビル1階", "lat": 35.439323, "lng": 139.363052, "reward": "4,000円", "budget": "", "url": "https://www2.ms-r.com/MSR/MonitorNew/MyPage/EntryInput.asp?InvitationID=4269226"}, {"name": "ふじ丸 回転寿司", "address": "神奈川県伊勢原市岡崎4855-1", "lat": 35.378559, "lng": 139.31842, "reward": "4,500円", "budget": "", "url": "https://www2.ms-r.com/MSR/MonitorNew/MyPage/EntryInput.asp?InvitationID=4176900"}, {"name": "やきとりのふじ丸 伊勢原店", "address": "神奈川県伊勢原市東大竹929-1", "lat": 35.384853, "lng": 139.316498, "reward": "4,500円", "budget": "", "url": "https://www2.ms-r.com/MSR/MonitorNew/MyPage/EntryInput.asp?InvitationID=4176865"}, {"name": "焼肉トラジ 海老名店", "address": "神奈川県海老名市めぐみ町２−２ ビナ ガーデンズテラス ４Ｆ", "lat": 35.454037, "lng": 139.390366, "reward": "8,500円", "budget": "", "url": "https://www2.ms-r.com/MSR/MonitorNew/MyPage/EntryInput.asp?InvitationID=4178849"}, {"name": "新時代 神奈川海老名店", "address": "神奈川県海老名市めぐみ町2番1号 Vinagarensterrace2階211号区画", "lat": 35.454037, "lng": 139.390366, "reward": "4,000円", "budget": "", "url": "https://www2.ms-r.com/MSR/MonitorNew/MyPage/EntryInput.asp?InvitationID=4300637"}, {"name": "新時代 長野駅前店", "address": "長野県長野市北石堂町1437-1", "lat": 36.71854, "lng": 138.165268, "reward": "4,000円", "budget": "", "url": "https://www2.ms-r.com/MSR/MonitorNew/MyPage/EntryInput.asp?InvitationID=4269185"}, {"name": "新時代 松本駅前店", "address": "長野県松本市中央区1丁目8-10", "lat": 36.232746, "lng": 137.965424, "reward": "4,000円", "budget": "", "url": "https://www2.ms-r.com/MSR/MonitorNew/MyPage/EntryInput.asp?InvitationID=4269236"}, {"name": "GALVESTON CLUB（ガルベストンクラブ）", "address": "新潟県新潟市中央区万代１丁目２-３ コープ野村万代 1F", "lat": 37.915684, "lng": 139.057495, "reward": "3,500円", "budget": "", "url": "https://www2.ms-r.com/MSR/MonitorNew/MyPage/EntryInput.asp?InvitationID=4334450"}, {"name": "新時代 新潟駅前店", "address": "新潟県新潟市中央区東大通一丁目1-10", "lat": 37.913628, "lng": 139.059998, "reward": "4,000円", "budget": "", "url": "https://www2.ms-r.com/MSR/MonitorNew/MyPage/EntryInput.asp?InvitationID=4269126"}, {"name": "本格沖縄料理いちゃりば！！ 新潟店", "address": "新潟県新潟市西区亀貝字堤715", "lat": 37.870163, "lng": 138.982666, "reward": "1,500円", "budget": "", "url": "https://www2.ms-r.com/MSR/MonitorNew/MyPage/EntryInput.asp?InvitationID=4264774"}, {"name": "新時代 新潟長岡駅前店", "address": "新潟県長岡市大手通2-2-3", "lat": 37.44849, "lng": 138.848648, "reward": "4,000円", "budget": "", "url": "https://www2.ms-r.com/MSR/MonitorNew/MyPage/EntryInput.asp?InvitationID=4269161"}, {"name": "新時代 新潟刈羽店", "address": "新潟県刈羽郡刈羽村下高町1663", "lat": 37.408241, "lng": 138.604919, "reward": "4,000円", "budget": "", "url": "https://www2.ms-r.com/MSR/MonitorNew/MyPage/EntryInput.asp?InvitationID=4269192"}, {"name": "新時代 富山駅店", "address": "富山県富山市明輪町1番220 とやﾏﾙｼｪのれん横町", "lat": 36.701214, "lng": 137.212143, "reward": "4,000円", "budget": "", "url": "https://www2.ms-r.com/MSR/MonitorNew/MyPage/EntryInput.asp?InvitationID=4269122"}, {"name": "新時代 富山クルン高岡店", "address": "富山県高岡市下関町6-1 クルン高岡B1", "lat": 36.742062, "lng": 137.015594, "reward": "4,000円", "budget": "", "url": "https://www2.ms-r.com/MSR/MonitorNew/MyPage/EntryInput.asp?InvitationID=4269203"}, {"name": "旬魚季菜 とと桜", "address": "石川県金沢市片町2-5-5　", "lat": 36.560883, "lng": 136.652512, "reward": "7,500円", "budget": "", "url": "https://www2.ms-r.com/MSR/MonitorNew/MyPage/EntryInput.asp?InvitationID=4249616"}, {"name": "新時代 金沢駅前店", "address": "石川県金沢市本町2丁目7-6 ｻｲｼﾞｮｳﾋﾞﾙ2階", "lat": 36.574295, "lng": 136.647736, "reward": "4,000円", "budget": "", "url": "https://www2.ms-r.com/MSR/MonitorNew/MyPage/EntryInput.asp?InvitationID=4269120"}, {"name": "La FESTa 鴨江店", "address": "静岡県浜松市中区鴨江3-11-3", "lat": 34.704788, "lng": 137.710495, "reward": "4,000円", "budget": "", "url": "https://www2.ms-r.com/MSR/MonitorNew/MyPage/EntryInput.asp?InvitationID=4212265"}, {"name": "てんぷらとぶり UOTEN", "address": "静岡県浜松市市中区田町329-12", "lat": 34.710808, "lng": 137.726303, "reward": "4,000円", "budget": "", "url": "https://www2.ms-r.com/MSR/MonitorNew/MyPage/EntryInput.asp?InvitationID=4212267"}, {"name": "創作鉄板居酒屋　情熱厨房てっぱん", "address": "静岡県浜松市市中区田町324－14", "lat": 34.710808, "lng": 137.726303, "reward": "4,000円", "budget": "", "url": "https://www2.ms-r.com/MSR/MonitorNew/MyPage/EntryInput.asp?InvitationID=4212268"}, {"name": "新時代 浜松駅前店", "address": "静岡県浜松市中央区千歳町95-9 花柳ビル1F", "lat": 34.703789, "lng": 137.731125, "reward": "4,000円", "budget": "", "url": "https://www2.ms-r.com/MSR/MonitorNew/MyPage/EntryInput.asp?InvitationID=4269215"}, {"name": "新時代 浜松鍛冶町店", "address": "静岡県浜松市中央区鍛冶町321-8 鍛冶町ビル2F", "lat": 34.705997, "lng": 137.730576, "reward": "4,000円", "budget": "", "url": "https://www2.ms-r.com/MSR/MonitorNew/MyPage/EntryInput.asp?InvitationID=4269241"}, {"name": "ゆうが 三島店", "address": "静岡県三島市一番町13-13 フジミビル4F", "lat": 35.125061, "lng": 138.912979, "reward": "3,000円", "budget": "", "url": "https://www2.ms-r.com/MSR/MonitorNew/MyPage/EntryInput.asp?InvitationID=4343272"}, {"name": "倉式珈琲店 イオンモール富士宮店", "address": "静岡県富士宮市浅間町1-8", "lat": 35.220619, "lng": 138.61351, "reward": "1,000円", "budget": "", "url": "https://www2.ms-r.com/MSR/MonitorNew/MyPage/EntryInput.asp?InvitationID=4263221"}, {"name": "新時代 掛川店", "address": "静岡県掛川市紺屋町6-7", "lat": 34.771648, "lng": 138.014832, "reward": "4,000円", "budget": "", "url": "https://www2.ms-r.com/MSR/MonitorNew/MyPage/EntryInput.asp?InvitationID=4269118"}, {"name": "御殿酒場", "address": "静岡県御殿場市新橋１８９８−３", "lat": 35.300591, "lng": 138.93454, "reward": "2,500円", "budget": "", "url": "https://www2.ms-r.com/MSR/MonitorNew/MyPage/EntryInput.asp?InvitationID=4332642"}, {"name": "新時代 今池本店", "address": "愛知県名古屋市千種区今池5丁目2-2", "lat": 35.168743, "lng": 136.937988, "reward": "4,000円", "budget": "", "url": "https://www2.ms-r.com/MSR/MonitorNew/MyPage/EntryInput.asp?InvitationID=4269200"}, {"name": "新時代 名駅西口椿町店", "address": "愛知県名古屋市中村区椿町4-11 神農ﾋﾞﾙ1F", "lat": 35.169998, "lng": 136.878235, "reward": "4,000円", "budget": "", "url": "https://www2.ms-r.com/MSR/MonitorNew/MyPage/EntryInput.asp?InvitationID=4269148"}, {"name": "焼肉トラジ 名古屋セントラルタワーズ店", "address": "愛知県名古屋市中村区名駅１丁目１−４ １２Ｆ", "lat": 35.17075, "lng": 136.883423, "reward": "8,500円", "budget": "", "url": "https://www2.ms-r.com/MSR/MonitorNew/MyPage/EntryInput.asp?InvitationID=4178836"}, {"name": "新時代44 名駅柳橋2号店", "address": "愛知県名古屋市中村区名駅4-13-15 矢田ﾋﾞﾙ2F", "lat": 35.169514, "lng": 136.88768, "reward": "4,000円", "budget": "", "url": "https://www2.ms-r.com/MSR/MonitorNew/MyPage/EntryInput.asp?InvitationID=4269245"}, {"name": "玄品 名古屋 錦本町", "address": "愛知県名古屋市中区錦2-12-8　", "lat": 35.171272, "lng": 136.901657, "reward": "2,000円", "budget": "", "url": "https://www2.ms-r.com/MSR/MonitorNew/MyPage/EntryInput.asp?InvitationID=4294621"}, {"name": "新時代 金山2号店", "address": "愛知県名古屋市中区金山1-13-8 ﾗｲｽﾞﾋﾞﾙ1F", "lat": 35.144737, "lng": 136.902603, "reward": "4,000円", "budget": "", "url": "https://www2.ms-r.com/MSR/MonitorNew/MyPage/EntryInput.asp?InvitationID=4269134"}, {"name": "新時代 八事店", "address": "愛知県名古屋市昭和区広路町字北石坂102-142", "lat": 35.137192, "lng": 136.964066, "reward": "4,000円", "budget": "", "url": "https://www2.ms-r.com/MSR/MonitorNew/MyPage/EntryInput.asp?InvitationID=4269156"}, {"name": "新時代 新瑞橋店", "address": "愛知県名古屋市瑞穂区瑞穂通8-7 ﾖｺｲﾋﾞﾙ1階", "lat": 35.118519, "lng": 136.936249, "reward": "4,000円", "budget": "", "url": "https://www2.ms-r.com/MSR/MonitorNew/MyPage/EntryInput.asp?InvitationID=4269119"}, {"name": "新時代 藤が丘駅前店", "address": "愛知県名古屋市名東区藤が丘60 スリーアイランドビル藤が丘1F", "lat": 35.184208, "lng": 137.019684, "reward": "4,000円", "budget": "", "url": "https://www2.ms-r.com/MSR/MonitorNew/MyPage/EntryInput.asp?InvitationID=4269220"}, {"name": "新時代 植田飯田街道店", "address": "愛知県名古屋市天白区植田3-1515", "lat": 35.127014, "lng": 136.989822, "reward": "4,000円", "budget": "", "url": "https://www2.ms-r.com/MSR/MonitorNew/MyPage/EntryInput.asp?InvitationID=4269138"}, {"name": "新時代 豊橋柱店", "address": "愛知県豊橋市柱三番町107番地", "lat": 34.748951, "lng": 137.37674, "reward": "4,000円", "budget": "", "url": "https://www2.ms-r.com/MSR/MonitorNew/MyPage/EntryInput.asp?InvitationID=4269227"}, {"name": "新時代 半田店", "address": "愛知県半田市有楽町7丁目91-1", "lat": 34.87233, "lng": 136.918579, "reward": "4,000円", "budget": "", "url": "https://www2.ms-r.com/MSR/MonitorNew/MyPage/EntryInput.asp?InvitationID=4269144"}, {"name": "新時代 豊川コロナ店", "address": "愛知県豊川市正岡町流田515番1", "lat": 34.802139, "lng": 137.386719, "reward": "4,000円", "budget": "", "url": "https://www2.ms-r.com/MSR/MonitorNew/MyPage/EntryInput.asp?InvitationID=4269240"}, {"name": "新時代 刈谷1号記念店", "address": "愛知県刈谷市丸田町4丁目1-1", "lat": 35.001541, "lng": 137.005341, "reward": "4,000円", "budget": "", "url": "https://www2.ms-r.com/MSR/MonitorNew/MyPage/EntryInput.asp?InvitationID=4269198"}, {"name": "新時代 豊田元町店", "address": "愛知県豊田市土橋町3丁目30", "lat": 35.061668, "lng": 137.130386, "reward": "4,000円", "budget": "", "url": "https://www2.ms-r.com/MSR/MonitorNew/MyPage/EntryInput.asp?InvitationID=4269230"}, {"name": "新時代 新豊田本店", "address": "愛知県豊田市若宮町8-1-7 ST.RITZ BLD 1F", "lat": 35.088215, "lng": 137.154282, "reward": "4,000円", "budget": "", "url": "https://www2.ms-r.com/MSR/MonitorNew/MyPage/EntryInput.asp?InvitationID=4269157"}, {"name": "新時代 豊田市駅前店", "address": "愛知県豊田市西町6丁目64", "lat": 35.086365, "lng": 137.155731, "reward": "4,000円", "budget": "", "url": "https://www2.ms-r.com/MSR/MonitorNew/MyPage/EntryInput.asp?InvitationID=4269178"}, {"name": "新時代 犬山駅前店", "address": "愛知県犬山市犬山東古券331-2 ﾍﾞﾙﾌｧｰ1 1F", "lat": 35.380253, "lng": 136.943222, "reward": "4,000円", "budget": "", "url": "https://www2.ms-r.com/MSR/MonitorNew/MyPage/EntryInput.asp?InvitationID=4269140"}, {"name": "新時代 常滑駅前店", "address": "愛知県常滑市鯉江本町5-140 ﾐｭｰﾌﾟﾗｯﾄ常滑", "lat": 34.889641, "lng": 136.835358, "reward": "4,000円", "budget": "", "url": "https://www2.ms-r.com/MSR/MonitorNew/MyPage/EntryInput.asp?InvitationID=4269139"}, {"name": "新時代 太田川駅前店", "address": "愛知県東海市大田町後田213-1 寺田ﾋﾞﾙ1階", "lat": 35.021095, "lng": 136.893738, "reward": "4,000円", "budget": "", "url": "https://www2.ms-r.com/MSR/MonitorNew/MyPage/EntryInput.asp?InvitationID=4269132"}, {"name": "新時代44 太田川駅前2号店", "address": "愛知県東海市大田町下浜田137 ﾕｳﾅﾙ東海103", "lat": 35.020657, "lng": 136.891647, "reward": "4,000円", "budget": "", "url": "https://www2.ms-r.com/MSR/MonitorNew/MyPage/EntryInput.asp?InvitationID=4269246"}, {"name": "炭火焼鳥 しげ 知立駅前店", "address": "愛知県知立市栄2-10 知立クロスゲートタワー 7Ｆ", "lat": 35.006737, "lng": 137.039581, "reward": "6,000円", "budget": "", "url": "https://www2.ms-r.com/MSR/MonitorNew/MyPage/EntryInput.asp?InvitationID=4300744"}, {"name": "新時代 尾張旭店", "address": "愛知県尾張旭市南栄町旭ケ丘42番8", "lat": 35.193977, "lng": 137.040527, "reward": "4,000円", "budget": "", "url": "https://www2.ms-r.com/MSR/MonitorNew/MyPage/EntryInput.asp?InvitationID=4269239"}, {"name": "新時代 高浜店", "address": "愛知県高浜市湯山町5-5-2", "lat": 34.932045, "lng": 137.000916, "reward": "4,000円", "budget": "", "url": "https://www2.ms-r.com/MSR/MonitorNew/MyPage/EntryInput.asp?InvitationID=4348927"}, {"name": "新時代 アスティ岐阜店", "address": "岐阜県岐阜市橋本町1-10-1", "lat": 35.409679, "lng": 136.754929, "reward": "4,000円", "budget": "", "url": "https://www2.ms-r.com/MSR/MonitorNew/MyPage/EntryInput.asp?InvitationID=4269131"}, {"name": "新時代 岐阜駅前玉宮店", "address": "岐阜県岐阜市住田町1丁目27 新岐阜堂1F", "lat": 35.411575, "lng": 136.758347, "reward": "4,000円", "budget": "", "url": "https://www2.ms-r.com/MSR/MonitorNew/MyPage/EntryInput.asp?InvitationID=4269206"}, {"name": "新時代 大垣駅前店", "address": "岐阜県大垣市高屋町1-4-4", "lat": 35.366264, "lng": 136.617996, "reward": "4,000円", "budget": "", "url": "https://www2.ms-r.com/MSR/MonitorNew/MyPage/EntryInput.asp?InvitationID=4269128"}, {"name": "新時代 多治見店", "address": "岐阜県多治見市若松町1-26-3", "lat": 35.340401, "lng": 137.115402, "reward": "4,000円", "budget": "", "url": "https://www2.ms-r.com/MSR/MonitorNew/MyPage/EntryInput.asp?InvitationID=4269137"}, {"name": "新時代 岐阜羽島店", "address": "岐阜県羽島市福寿町本郷字千代田105-2", "lat": 35.323627, "lng": 136.688507, "reward": "4,000円", "budget": "", "url": "https://www2.ms-r.com/MSR/MonitorNew/MyPage/EntryInput.asp?InvitationID=4269141"}, {"name": "ちょぼ蔵", "address": "岐阜県海津市平田町三郷１９８４ー２", "lat": 35.264015, "lng": 136.646851, "reward": "1,000円", "budget": "", "url": "https://www2.ms-r.com/MSR/MonitorNew/MyPage/EntryInput.asp?InvitationID=4346330"}, {"name": "牛角焼肉食堂 イオンモール津南店", "address": "三重県津市高茶屋小森町145番地 イオンモール津南3階", "lat": 34.670269, "lng": 136.517746, "reward": "1,000円", "budget": "", "url": "https://www2.ms-r.com/MSR/MonitorNew/MyPage/EntryInput.asp?InvitationID=4294626"}, {"name": "新時代 津駅前店", "address": "三重県津市羽所町700", "lat": 34.735172, "lng": 136.510681, "reward": "4,000円", "budget": "", "url": "https://www2.ms-r.com/MSR/MonitorNew/MyPage/EntryInput.asp?InvitationID=4269130"}, {"name": "新時代 三重大前店", "address": "三重県津市栗真町屋町1702-9", "lat": 34.74712, "lng": 136.519455, "reward": "4,000円", "budget": "", "url": "https://www2.ms-r.com/MSR/MonitorNew/MyPage/EntryInput.asp?InvitationID=4269136"}, {"name": "新時代 白子駅前店", "address": "三重県鈴鹿市白子駅前15-10 松下ﾋﾞﾙ1階", "lat": 34.835457, "lng": 136.589996, "reward": "4,000円", "budget": "", "url": "https://www2.ms-r.com/MSR/MonitorNew/MyPage/EntryInput.asp?InvitationID=4269127"}, {"name": "新時代 三重朝日店", "address": "三重県三重郡朝日町小向字御用308-1", "lat": 35.034805, "lng": 136.668152, "reward": "4,000円", "budget": "", "url": "https://www2.ms-r.com/MSR/MonitorNew/MyPage/EntryInput.asp?InvitationID=4269142"}, {"name": "お好み焼・鉄板焼 中々", "address": "京都府京都市中京区西ノ京北聖町25　HFMビル2F", "lat": 35.011555, "lng": 135.743134, "reward": "4,000円", "budget": "", "url": "https://www2.ms-r.com/MSR/MonitorNew/MyPage/EntryInput.asp?InvitationID=4251386"}, {"name": "とりくら", "address": "京都府京都市中京区錦小路烏丸東入ル元法然寺町すぎむらビル1F", "lat": 35.004276, "lng": 135.74881, "reward": "5,500円", "budget": "", "url": "https://www2.ms-r.com/MSR/MonitorNew/MyPage/EntryInput.asp?InvitationID=4251387"}, {"name": "京もつ鍋 秀寅", "address": "京都府京都市中京区錦小路通室町東入ル占出山町310 ヤママス錦プラザ 2F", "lat": 35.004276, "lng": 135.74881, "reward": "5,500円", "budget": "", "url": "https://www2.ms-r.com/MSR/MonitorNew/MyPage/EntryInput.asp?InvitationID=4251388"}, {"name": "もつ鍋 先斗町 亀八", "address": "京都府京都市中京区木屋町通り三条下ル材木町185-3", "lat": 35.014957, "lng": 135.766159, "reward": "5,500円", "budget": "", "url": "https://www2.ms-r.com/MSR/MonitorNew/MyPage/EntryInput.asp?InvitationID=4251389"}, {"name": "もつ鍋 先斗町 亀八 別館", "address": "京都府京都市中京区先斗町通り四条上ル下樵木町208-3", "lat": 35.009998, "lng": 135.751389, "reward": "5,500円", "budget": "", "url": "https://www2.ms-r.com/MSR/MonitorNew/MyPage/EntryInput.asp?InvitationID=4251390"}, {"name": "京もつ鍋 はなはな", "address": "京都府京都市中京区西ノ京職司町26-12　アパル御池1F", "lat": 35.010811, "lng": 135.743195, "reward": "5,500円", "budget": "", "url": "https://www2.ms-r.com/MSR/MonitorNew/MyPage/EntryInput.asp?InvitationID=4251391"}, {"name": "あごつゆしゃぶしゃぶ 山福", "address": "京都府京都市中京区材木町187", "lat": 35.00687, "lng": 135.770782, "reward": "5,000円", "budget": "", "url": "https://www2.ms-r.com/MSR/MonitorNew/MyPage/EntryInput.asp?InvitationID=4251392"}, {"name": "新時代 四条河原町店", "address": "京都府京都市中京区河原町通四条上がる二丁目塩谷町336番地 志津屋四条河原町ビル", "lat": 35.009998, "lng": 135.751389, "reward": "4,000円", "budget": "", "url": "https://www2.ms-r.com/MSR/MonitorNew/MyPage/EntryInput.asp?InvitationID=4269209"}, {"name": "新時代 京都木屋町店", "address": "京都府京都市中京区山崎町258-21", "lat": 35.007175, "lng": 135.768921, "reward": "4,000円", "budget": "", "url": "https://www2.ms-r.com/MSR/MonitorNew/MyPage/EntryInput.asp?InvitationID=4269219"}, {"name": "山下醤造", "address": "京都府京都市中京区西ノ京職司町19", "lat": 35.01041, "lng": 135.743286, "reward": "1,000円", "budget": "", "url": "https://www2.ms-r.com/MSR/MonitorNew/MyPage/EntryInput.asp?InvitationID=4251466"}, {"name": "新時代 京都西院店", "address": "京都府京都市右京区西院巽町2-2 オヴェスト西院2F", "lat": 35.003296, "lng": 135.730728, "reward": "4,000円", "budget": "", "url": "https://www2.ms-r.com/MSR/MonitorNew/MyPage/EntryInput.asp?InvitationID=4269234"}, {"name": "串勝 六角屋", "address": "京都府京都市山科区竹鼻竹ノ街道町77-1", "lat": 34.989368, "lng": 135.815521, "reward": "5,500円", "budget": "", "url": "https://www2.ms-r.com/MSR/MonitorNew/MyPage/EntryInput.asp?InvitationID=4251395"}, {"name": "LionCAFE", "address": "京都府京都市山科区竹鼻竹乃街道町74 アースビル3階", "lat": 34.989368, "lng": 135.815521, "reward": "2,500円", "budget": "", "url": "https://www2.ms-r.com/MSR/MonitorNew/MyPage/EntryInput.asp?InvitationID=4251467"}, {"name": "もつ鍋 亀八 山科店", "address": "京都府京都市山科区竹鼻竹ノ街道町65-1", "lat": 34.990303, "lng": 135.815674, "reward": "5,500円", "budget": "", "url": "https://www2.ms-r.com/MSR/MonitorNew/MyPage/EntryInput.asp?InvitationID=4251393"}, {"name": "新時代 大阪福島駅前店", "address": "大阪府大阪市福島区福島7丁目1-1", "lat": 34.697182, "lng": 135.486893, "reward": "4,000円", "budget": "", "url": "https://www2.ms-r.com/MSR/MonitorNew/MyPage/EntryInput.asp?InvitationID=4269190"}, {"name": "魚屋 十忠八九", "address": "大阪府大阪市福島区福島7-2-6 ふくまる通り57", "lat": 34.696358, "lng": 135.485077, "reward": "5,000円", "budget": "", "url": "https://www2.ms-r.com/MSR/MonitorNew/MyPage/EntryInput.asp?InvitationID=4325216"}, {"name": "福島呑場ヒンジ", "address": "大阪府大阪市福島区福島7-1-6 1F", "lat": 34.696957, "lng": 135.486435, "reward": "5,000円", "budget": "", "url": "https://www2.ms-r.com/MSR/MonitorNew/MyPage/EntryInput.asp?InvitationID=4325217"}, {"name": "二階の洋品店", "address": "大阪府大阪市福島区福島7-1-6 2F", "lat": 34.696957, "lng": 135.486435, "reward": "5,000円", "budget": "", "url": "https://www2.ms-r.com/MSR/MonitorNew/MyPage/EntryInput.asp?InvitationID=4325218"}, {"name": "季楽酒場 おっきゃがり", "address": "大阪府大阪市福島区福島7丁目2番6号", "lat": 34.696358, "lng": 135.485077, "reward": "5,000円", "budget": "", "url": "https://www2.ms-r.com/MSR/MonitorNew/MyPage/EntryInput.asp?InvitationID=4325219"}, {"name": "焼鳥 とり藤  福島店", "address": "大阪府大阪市福島区福島5-14-12 稲垣ビルプラザ2　1階", "lat": 34.697037, "lng": 135.486801, "reward": "5,000円", "budget": "", "url": "https://www2.ms-r.com/MSR/MonitorNew/MyPage/EntryInput.asp?InvitationID=4325214"}, {"name": "鮨 いとう", "address": "大阪府大阪市福島区福島7-8-3 福本ビル101", "lat": 34.697727, "lng": 135.486557, "reward": "12,500円", "budget": "", "url": "https://www2.ms-r.com/MSR/MonitorNew/MyPage/EntryInput.asp?InvitationID=4325223"}, {"name": "台湾小籠包 台湾小籠包　天王寺MIO店", "address": "大阪府大阪市天王寺区悲田院町10-39", "lat": 34.647064, "lng": 135.513474, "reward": "1,000円", "budget": "", "url": "https://www2.ms-r.com/MSR/MonitorNew/MyPage/EntryInput.asp?InvitationID=4233629"}, {"name": "新時代 大阪難波なんさん通り店", "address": "大阪府大阪市浪速区日本橋3丁目6−24 MIMARU大阪 難波STATION 1F", "lat": 34.663044, "lng": 135.505386, "reward": "4,000円", "budget": "", "url": "https://www2.ms-r.com/MSR/MonitorNew/MyPage/EntryInput.asp?InvitationID=4269180"}, {"name": "囲炉裏のおっきゃがり", "address": "大阪府大阪市阿倍野区阿倍野筋2-1-18 アートキューブ高橋ビル", "lat": 34.644001, "lng": 135.513016, "reward": "6,500円", "budget": "", "url": "https://www2.ms-r.com/MSR/MonitorNew/MyPage/EntryInput.asp?InvitationID=4325228"}, {"name": "新時代 大阪十三駅西口店", "address": "大阪府大阪市淀川区十三本町1丁目9-2 1F102", "lat": 34.71917, "lng": 135.480728, "reward": "4,000円", "budget": "", "url": "https://www2.ms-r.com/MSR/MonitorNew/MyPage/EntryInput.asp?InvitationID=4269197"}, {"name": "お初の十忠八九", "address": "大阪府大阪市北区曽根崎2-13-3 ANビル 1F", "lat": 34.700871, "lng": 135.500107, "reward": "5,000円", "budget": "", "url": "https://www2.ms-r.com/MSR/MonitorNew/MyPage/EntryInput.asp?InvitationID=4325205"}, {"name": "焼肉トラジ 大阪ヒルトンプラザウエスト店", "address": "大阪府大阪市北区梅田２丁目２−２ ヒルトンプラザウエスト Ｂ２Ｆ", "lat": 34.699486, "lng": 135.495316, "reward": "8,500円", "budget": "", "url": "https://www2.ms-r.com/MSR/MonitorNew/MyPage/EntryInput.asp?InvitationID=4178838"}, {"name": "焼肉トラジ ルクア大阪店", "address": "大阪府大阪市北区梅田３丁目１−３ ルクア大阪 Ｂ２Ｆ", "lat": 34.701881, "lng": 135.496338, "reward": "8,500円", "budget": "", "url": "https://www2.ms-r.com/MSR/MonitorNew/MyPage/EntryInput.asp?InvitationID=4178839"}, {"name": "京もつ鍋亀八 お初天神裏参道店", "address": "大阪府大阪市北区曽根崎2-10-9 2階", "lat": 34.700451, "lng": 135.500824, "reward": "4,500円", "budget": "", "url": "https://www2.ms-r.com/MSR/MonitorNew/MyPage/EntryInput.asp?InvitationID=4251394"}, {"name": "新時代 大阪天満店", "address": "大阪府大阪市北区天神橋四丁目12-4 天満ｼﾐｽﾞﾋﾞﾙ1階", "lat": 34.70562, "lng": 135.511765, "reward": "4,000円", "budget": "", "url": "https://www2.ms-r.com/MSR/MonitorNew/MyPage/EntryInput.asp?InvitationID=4269124"}, {"name": "新時代 大阪梅田2号店", "address": "大阪府大阪市北区堂山町4-12 白馬車ビル1F", "lat": 34.70266, "lng": 135.502106, "reward": "4,000円", "budget": "", "url": "https://www2.ms-r.com/MSR/MonitorNew/MyPage/EntryInput.asp?InvitationID=4269205"}, {"name": "新時代 大阪梅田店", "address": "大阪府大阪市北区堂山町4-6", "lat": 34.702255, "lng": 135.502243, "reward": "4,000円", "budget": "", "url": "https://www2.ms-r.com/MSR/MonitorNew/MyPage/EntryInput.asp?InvitationID=4269164"}, {"name": "新時代 大阪堂島", "address": "大阪府大阪市北区堂島2-1-39 日食物産ﾋﾞﾙ1階", "lat": 34.696232, "lng": 135.495361, "reward": "4,000円", "budget": "", "url": "https://www2.ms-r.com/MSR/MonitorNew/MyPage/EntryInput.asp?InvitationID=4269172"}, {"name": "お初の十忠八九", "address": "大阪府大阪市北区曽根崎2-13-3 ANビル 1F", "lat": 34.700871, "lng": 135.500107, "reward": "5,000円", "budget": "", "url": "https://www2.ms-r.com/MSR/MonitorNew/MyPage/EntryInput.asp?InvitationID=4325229"}, {"name": "焼鳥 とり藤  お初天神店", "address": "大阪府大阪市北区曽根崎2-7-15", "lat": 34.699623, "lng": 135.500534, "reward": "5,000円", "budget": "", "url": "https://www2.ms-r.com/MSR/MonitorNew/MyPage/EntryInput.asp?InvitationID=4325215"}, {"name": "うたげどころ うおっしゅ", "address": "大阪府大阪市北区曽根崎新地2-3-13 若杉大阪駅前ビル　Ｂ１Ｆ", "lat": 34.697739, "lng": 135.493637, "reward": "6,500円", "budget": "", "url": "https://www2.ms-r.com/MSR/MonitorNew/MyPage/EntryInput.asp?InvitationID=4325220"}, {"name": "酒場 ばんと", "address": "大阪府大阪市北区芝田1-1-3 阪急三番街 1F", "lat": 34.70414, "lng": 135.499008, "reward": "4,000円", "budget": "", "url": "https://www2.ms-r.com/MSR/MonitorNew/MyPage/EntryInput.asp?InvitationID=4325221"}, {"name": "新時代 大阪難波店", "address": "大阪府大阪市中央区難波3丁目4-14 岸田ビル1F・2F", "lat": 34.666878, "lng": 135.501816, "reward": "4,000円", "budget": "", "url": "https://www2.ms-r.com/MSR/MonitorNew/MyPage/EntryInput.asp?InvitationID=4269221"}, {"name": "浪速炉ばた 東洋小噺", "address": "大阪府大阪市中央区難波4-2-13", "lat": 34.666447, "lng": 135.499466, "reward": "7,500円", "budget": "", "url": "https://www2.ms-r.com/MSR/MonitorNew/MyPage/EntryInput.asp?InvitationID=4325233"}, {"name": "なにわ寿し", "address": "大阪府大阪市中央区難波4-8-8", "lat": 34.666336, "lng": 135.498856, "reward": "5,000円", "budget": "", "url": "https://www2.ms-r.com/MSR/MonitorNew/MyPage/EntryInput.asp?InvitationID=4325234"}, {"name": "生ハムとPIZZA。86ストア", "address": "大阪府大阪市中央区難波千日前14-18 道具屋筋横丁", "lat": 34.663574, "lng": 135.503296, "reward": "7,500円", "budget": "", "url": "https://www2.ms-r.com/MSR/MonitorNew/MyPage/EntryInput.asp?InvitationID=4345645"}, {"name": "みなみの十忠八九", "address": "大阪府大阪市中央区難波4-2-6 トシヒサビル 1F・2F", "lat": 34.666229, "lng": 135.499924, "reward": "5,000円", "budget": "", "url": "https://www2.ms-r.com/MSR/MonitorNew/MyPage/EntryInput.asp?InvitationID=4325227"}, {"name": "焼肉 肉どうし  北浜本店", "address": "大阪府大阪市中央区今橋2-2-11 大和今橋ビル", "lat": 34.690109, "lng": 135.505722, "reward": "7,000円", "budget": "", "url": "https://www2.ms-r.com/MSR/MonitorNew/MyPage/EntryInput.asp?InvitationID=4325212"}, {"name": "焼肉 肉どうし  裏難波店", "address": "大阪府大阪市中央区難波千日前１４-６ 太星食器ビル別館B区画", "lat": 34.663773, "lng": 135.50354, "reward": "7,000円", "budget": "", "url": "https://www2.ms-r.com/MSR/MonitorNew/MyPage/EntryInput.asp?InvitationID=4325213"}, {"name": "新時代 大阪阪大前店", "address": "大阪府池田市石橋2丁目2-12 ます井ビル", "lat": 34.808605, "lng": 135.446198, "reward": "4,000円", "budget": "", "url": "https://www2.ms-r.com/MSR/MonitorNew/MyPage/EntryInput.asp?InvitationID=4269212"}, {"name": "新時代 大阪関大前店", "address": "大阪府吹田市千里山東1-7-22", "lat": 34.773285, "lng": 135.505997, "reward": "4,000円", "budget": "", "url": "https://www2.ms-r.com/MSR/MonitorNew/MyPage/EntryInput.asp?InvitationID=4269143"}, {"name": "新時代 大阪阪急高槻駅前店", "address": "大阪府高槻市城北町2-4-15 MOビル1F", "lat": 34.849449, "lng": 135.623566, "reward": "4,000円", "budget": "", "url": "https://www2.ms-r.com/MSR/MonitorNew/MyPage/EntryInput.asp?InvitationID=4269183"}, {"name": "バケット バケット イオンモール大日店", "address": "大阪府守口市大日東町１－１８", "lat": 34.749195, "lng": 135.579391, "reward": "1,000円", "budget": "", "url": "https://www2.ms-r.com/MSR/MonitorNew/MyPage/EntryInput.asp?InvitationID=4225116"}, {"name": "焼肉・冷麺　肉どうし　松苑", "address": "大阪府松原市三宅西3-269-1", "lat": 34.587444, "lng": 135.549881, "reward": "7,000円", "budget": "", "url": "https://www2.ms-r.com/MSR/MonitorNew/MyPage/EntryInput.asp?InvitationID=4325230"}, {"name": "ビストロ BISTRO309 ららぽーと和泉店", "address": "大阪府和泉市あゆみ野4-4-7", "lat": 34.435585, "lng": 135.448669, "reward": "1,000円", "budget": "", "url": "https://www2.ms-r.com/MSR/MonitorNew/MyPage/EntryInput.asp?InvitationID=4225160"}, {"name": "新時代 大阪近大前店", "address": "大阪府東大阪市小若江3丁目7番3号", "lat": 34.651546, "lng": 135.585556, "reward": "4,000円", "budget": "", "url": "https://www2.ms-r.com/MSR/MonitorNew/MyPage/EntryInput.asp?InvitationID=4269151"}, {"name": "新時代 阪急三宮駅西口店", "address": "兵庫県神戸市中央区北長挟通2-12-10", "lat": 34.69331, "lng": 135.192429, "reward": "4,000円", "budget": "", "url": "https://www2.ms-r.com/MSR/MonitorNew/MyPage/EntryInput.asp?InvitationID=4269193"}, {"name": "まるまさ家 姫路本店", "address": "兵庫県姫路市南町８", "lat": 34.829113, "lng": 134.688614, "reward": "7,000円", "budget": "", "url": "https://www2.ms-r.com/MSR/MonitorNew/MyPage/EntryInput.asp?InvitationID=4347288"}, {"name": "喫茶ラヴリ＆YORU NO MARUMASA", "address": "兵庫県姫路市駅前町１８８－１ 駅前地下街", "lat": 34.827621, "lng": 134.690842, "reward": "7,000円", "budget": "", "url": "https://www2.ms-r.com/MSR/MonitorNew/MyPage/EntryInput.asp?InvitationID=4347297"}, {"name": "姫路タンメン", "address": "兵庫県姫路市駅前町２２９", "lat": 34.827621, "lng": 134.690842, "reward": "7,000円", "budget": "", "url": "https://www2.ms-r.com/MSR/MonitorNew/MyPage/EntryInput.asp?InvitationID=4347300"}, {"name": "大衆酒場ニューマルマサ", "address": "兵庫県姫路市立町１４ 第１７クリスタルビル１Ｆ", "lat": 34.830883, "lng": 134.689743, "reward": "7,000円", "budget": "", "url": "https://www2.ms-r.com/MSR/MonitorNew/MyPage/EntryInput.asp?InvitationID=4347303"}, {"name": "MARUMASA花鳥風月", "address": "兵庫県姫路市塩町２０５ 塩町くりすたる横丁東館１Ｆ", "lat": 34.831394, "lng": 134.687271, "reward": "7,000円", "budget": "", "url": "https://www2.ms-r.com/MSR/MonitorNew/MyPage/EntryInput.asp?InvitationID=4347306"}, {"name": "大阪王将 阪神尼崎駅前店", "address": "兵庫県尼崎市神田中通2-28　", "lat": 34.719494, "lng": 135.415604, "reward": "1,000円", "budget": "", "url": "https://www2.ms-r.com/MSR/MonitorNew/MyPage/EntryInput.asp?InvitationID=4168974"}, {"name": "新時代 阪神尼崎駅北口店", "address": "兵庫県尼崎市神田中通2丁目18−1", "lat": 34.719738, "lng": 135.415695, "reward": "4,000円", "budget": "", "url": "https://www2.ms-r.com/MSR/MonitorNew/MyPage/EntryInput.asp?InvitationID=4269179"}, {"name": "和楽心 魚住店", "address": "兵庫県明石市魚住町長坂寺769-2", "lat": 34.69738, "lng": 134.915222, "reward": "5,000円", "budget": "", "url": "https://www2.ms-r.com/MSR/MonitorNew/MyPage/EntryInput.asp?InvitationID=4189922"}, {"name": "サンマルクカフェ ＜20271＞奈良三条店", "address": "奈良県奈良市三条町499-1F＆Fビル", "lat": 34.681595, "lng": 135.821198, "reward": "1,000円", "budget": "", "url": "https://www2.ms-r.com/MSR/MonitorNew/MyPage/EntryInput.asp?InvitationID=4239150"}, {"name": "ととぎん 近鉄奈良駅前店", "address": "奈良県奈良市東向中町5-1", "lat": 34.683792, "lng": 135.828918, "reward": "3,000円", "budget": "", "url": "https://www2.ms-r.com/MSR/MonitorNew/MyPage/EntryInput.asp?InvitationID=4189472"}, {"name": "新時代 島根松江店", "address": "島根県松江市寺町198-57 ボートピアビル1F", "lat": 35.464554, "lng": 133.057388, "reward": "4,000円", "budget": "", "url": "https://www2.ms-r.com/MSR/MonitorNew/MyPage/EntryInput.asp?InvitationID=4290072"}, {"name": "新時代 鳥取米子駅前店", "address": "鳥取県米子市明治町250 児玉ビル2F", "lat": 35.423656, "lng": 133.335022, "reward": "4,000円", "budget": "", "url": "https://www2.ms-r.com/MSR/MonitorNew/MyPage/EntryInput.asp?InvitationID=4269214"}, {"name": "炉端かば 倉吉店", "address": "鳥取県倉吉市上井町2-10-7", "lat": 35.454079, "lng": 133.848145, "reward": "7,000円", "budget": "", "url": "https://www2.ms-r.com/MSR/MonitorNew/MyPage/EntryInput.asp?InvitationID=4346660"}, {"name": "新時代 岡山本町店", "address": "岡山県岡山市北区本町4-21 M.Y.Bldg.Eestビル2F", "lat": 34.664658, "lng": 133.921753, "reward": "4,000円", "budget": "", "url": "https://www2.ms-r.com/MSR/MonitorNew/MyPage/EntryInput.asp?InvitationID=4269244"}, {"name": "新時代 広島立町店", "address": "広島県広島市中区立町4-3 ﾊﾟﾘｼﾞｪﾝﾇﾋﾞﾙ1階", "lat": 34.393593, "lng": 132.460938, "reward": "4,000円", "budget": "", "url": "https://www2.ms-r.com/MSR/MonitorNew/MyPage/EntryInput.asp?InvitationID=4269121"}, {"name": "新時代 広島胡町店", "address": "広島県広島市中区胡町3-25 ﾊﾞｲｵﾚｯﾄﾋﾞﾙ1階", "lat": 34.392792, "lng": 132.465347, "reward": "4,000円", "budget": "", "url": "https://www2.ms-r.com/MSR/MonitorNew/MyPage/EntryInput.asp?InvitationID=4269123"}, {"name": "新時代 広島福山元町店", "address": "広島県福山市元町15－31", "lat": 34.487736, "lng": 133.365601, "reward": "4,000円", "budget": "", "url": "https://www2.ms-r.com/MSR/MonitorNew/MyPage/EntryInput.asp?InvitationID=4269188"}, {"name": "THE DAILY.", "address": "山口県防府市千日2-5-18", "lat": 34.060234, "lng": 131.562241, "reward": "2,000円", "budget": "", "url": "https://www2.ms-r.com/MSR/MonitorNew/MyPage/EntryInput.asp?InvitationID=4345530"}, {"name": "炭火焼鳥　しゃかりき", "address": "山口県周南市飯島町2丁目16", "lat": 34.050156, "lng": 131.807907, "reward": "8,000円", "budget": "", "url": "https://www2.ms-r.com/MSR/MonitorNew/MyPage/EntryInput.asp?InvitationID=4338826"}, {"name": "蔵々 創和彩蔵々　周南店", "address": "山口県周南市若宮町１丁目29", "lat": 34.052521, "lng": 131.808136, "reward": "8,000円", "budget": "", "url": "https://www2.ms-r.com/MSR/MonitorNew/MyPage/EntryInput.asp?InvitationID=4338814"}, {"name": "新時代 山口徳山店", "address": "山口県周南市銀座2-18 銀座毎日興業ビル 2F", "lat": 34.050205, "lng": 131.805313, "reward": "4,000円", "budget": "", "url": "https://www2.ms-r.com/MSR/MonitorNew/MyPage/EntryInput.asp?InvitationID=4348926"}, {"name": "新時代 愛媛松山大街道店", "address": "愛媛県松山市大街道2丁目3番地11 マサキビル", "lat": 33.839588, "lng": 132.770004, "reward": "4,000円", "budget": "", "url": "https://www2.ms-r.com/MSR/MonitorNew/MyPage/EntryInput.asp?InvitationID=4269213"}, {"name": "新時代 博多駅前店", "address": "福岡県福岡市博多区博多駅前三丁目26-13", "lat": 33.589203, "lng": 130.415924, "reward": "4,000円", "budget": "", "url": "https://www2.ms-r.com/MSR/MonitorNew/MyPage/EntryInput.asp?InvitationID=4269125"}, {"name": "新時代 博多駅東店", "address": "福岡県福岡市博多区博多駅東二丁目6-15 やまとやﾋﾞﾙ", "lat": 33.587257, "lng": 130.424118, "reward": "4,000円", "budget": "", "url": "https://www2.ms-r.com/MSR/MonitorNew/MyPage/EntryInput.asp?InvitationID=4269133"}, {"name": "満福れーめん", "address": "福岡県福岡市中央区今泉1-12-23 西鉄今泉ビル 2F", "lat": 33.586903, "lng": 130.400681, "reward": "1,000円", "budget": "", "url": "https://www2.ms-r.com/MSR/MonitorNew/MyPage/EntryInput.asp?InvitationID=4345043"}, {"name": "まつり", "address": "福岡県福岡市中央区春吉3-25-3 白亜荘1F", "lat": 33.587982, "lng": 130.406403, "reward": "7,000円", "budget": "", "url": "https://www2.ms-r.com/MSR/MonitorNew/MyPage/EntryInput.asp?InvitationID=4312249"}, {"name": "焼肉トラジ 天神店", "address": "福岡県福岡市中央区天神２丁目８−４９ ヒューリックスクエア福岡天神 2階", "lat": 33.590679, "lng": 130.397797, "reward": "8,500円", "budget": "", "url": "https://www2.ms-r.com/MSR/MonitorNew/MyPage/EntryInput.asp?InvitationID=4178873"}, {"name": "新時代 福岡天神店", "address": "福岡県福岡市中央区今泉1-19-18 楽天地ﾋﾞﾙ1F", "lat": 33.586292, "lng": 130.397308, "reward": "4,000円", "budget": "", "url": "https://www2.ms-r.com/MSR/MonitorNew/MyPage/EntryInput.asp?InvitationID=4269150"}, {"name": "新時代 福岡今泉店", "address": "福岡県福岡市中央区今泉1丁目13-29", "lat": 33.586792, "lng": 130.400452, "reward": "4,000円", "budget": "", "url": "https://www2.ms-r.com/MSR/MonitorNew/MyPage/EntryInput.asp?InvitationID=4269207"}, {"name": "新時代 西鉄久留米駅前店", "address": "福岡県久留米市東町33-5 ﾆｭｰﾌﾀﾏﾀ第3ﾋﾞﾙ", "lat": 33.312294, "lng": 130.518829, "reward": "4,000円", "budget": "", "url": "https://www2.ms-r.com/MSR/MonitorNew/MyPage/EntryInput.asp?InvitationID=4269146"}, {"name": "禄", "address": "佐賀県佐賀市愛敬町１３−１３", "lat": 33.262524, "lng": 130.301285, "reward": "8,500円", "budget": "", "url": "https://www2.ms-r.com/MSR/MonitorNew/MyPage/EntryInput.asp?InvitationID=4152546"}, {"name": "新時代 佐賀駅北口店", "address": "佐賀県佐賀市駅前中央1丁目13−20", "lat": 33.264488, "lng": 130.297623, "reward": "4,000円", "budget": "", "url": "https://www2.ms-r.com/MSR/MonitorNew/MyPage/EntryInput.asp?InvitationID=4269181"}, {"name": "新時代 長崎思案橋店", "address": "長崎県長崎市鍛冶屋町6番1号かじやまち六番館ﾋﾞﾙ 1階", "lat": 32.743763, "lng": 129.880737, "reward": "4,000円", "budget": "", "url": "https://www2.ms-r.com/MSR/MonitorNew/MyPage/EntryInput.asp?InvitationID=4269165"}, {"name": "ジョイフル 長崎五島店", "address": "長崎県五島市籠淵町2038番地6", "lat": 32.694378, "lng": 128.811493, "reward": "3,000円", "budget": "", "url": "https://www2.ms-r.com/MSR/MonitorNew/MyPage/EntryInput.asp?InvitationID=4255587"}, {"name": "ジョイフル 長崎五島店", "address": "長崎県五島市籠淵町2038番地6", "lat": 32.694378, "lng": 128.811493, "reward": "3,500円", "budget": "", "url": "https://www2.ms-r.com/MSR/MonitorNew/MyPage/EntryInput.asp?InvitationID=4255588"}, {"name": "新時代 大分別府駅前店", "address": "大分県別府市駅前本町1-4 Plaza一番街1F", "lat": 33.279552, "lng": 131.502243, "reward": "4,000円", "budget": "", "url": "https://www2.ms-r.com/MSR/MonitorNew/MyPage/EntryInput.asp?InvitationID=4269229"}, {"name": "酔っ手羽 熊本下通店", "address": "熊本県熊本市中央区下通2-1-32 ODA下通ビル 1F・2F・3F", "lat": 32.799667, "lng": 130.707962, "reward": "5,000円", "budget": "", "url": "https://www2.ms-r.com/MSR/MonitorNew/MyPage/EntryInput.asp?InvitationID=4218012"}, {"name": "新時代 熊本下通店", "address": "熊本県熊本市中央区新市街3-10 ﾆｭｰﾌﾛﾝﾃｨｱﾋﾞﾙ1、2階", "lat": 32.79977, "lng": 130.707764, "reward": "4,000円", "budget": "", "url": "https://www2.ms-r.com/MSR/MonitorNew/MyPage/EntryInput.asp?InvitationID=4269152"}, {"name": "新時代 熊本下通り2号店", "address": "熊本県熊本市中央区下通1丁目3−6ﾌﾀﾊﾞﾋﾞﾙ2F", "lat": 32.802433, "lng": 130.70932, "reward": "4,000円", "budget": "", "url": "https://www2.ms-r.com/MSR/MonitorNew/MyPage/EntryInput.asp?InvitationID=4269173"}, {"name": "大漁食堂あおさ ー", "address": "熊本県天草市牛深町2286-116　道の駅 うしぶか海彩館 2F", "lat": 32.194366, "lng": 130.024597, "reward": "4,500円", "budget": "", "url": "https://www2.ms-r.com/MSR/MonitorNew/MyPage/EntryInput.asp?InvitationID=4294969"}, {"name": "新時代 宮崎橘通店", "address": "宮崎県宮崎市橘通東3丁目2-5", "lat": 31.914494, "lng": 131.42308, "reward": "4,000円", "budget": "", "url": "https://www2.ms-r.com/MSR/MonitorNew/MyPage/EntryInput.asp?InvitationID=4269160"}, {"name": "季節料理×お酒　結い 都城店", "address": "宮崎県都城市栄町6-14-1 吉座ビル1F", "lat": 31.73568, "lng": 131.075409, "reward": "8,500円", "budget": "", "url": "https://www2.ms-r.com/MSR/MonitorNew/MyPage/EntryInput.asp?InvitationID=4332722"}, {"name": "こんぴら丸 谷山本店", "address": "鹿児島県鹿児島市南栄5-10-1 コンフォートイン鹿児島谷山 1F", "lat": 31.506332, "lng": 130.516617, "reward": "2,500円", "budget": "", "url": "https://www2.ms-r.com/MSR/MonitorNew/MyPage/EntryInput.asp?InvitationID=4347345"}, {"name": "新時代 鹿児島中央駅東口店", "address": "鹿児島県鹿児島市中央町2-5", "lat": 31.585926, "lng": 130.543381, "reward": "4,000円", "budget": "", "url": "https://www2.ms-r.com/MSR/MonitorNew/MyPage/EntryInput.asp?InvitationID=4269204"}, {"name": "新時代 鹿児島天文館店", "address": "鹿児島県鹿児島市千日町9-9 朝隈ビル1F", "lat": 31.588976, "lng": 130.555939, "reward": "4,000円", "budget": "", "url": "https://www2.ms-r.com/MSR/MonitorNew/MyPage/EntryInput.asp?InvitationID=4269228"}, {"name": "新時代 那覇久茂地店", "address": "沖縄県那覇市久茂地3丁目12-4 ラフテビル2F", "lat": 26.215172, "lng": 127.681885, "reward": "4,000円", "budget": "", "url": "https://www2.ms-r.com/MSR/MonitorNew/MyPage/EntryInput.asp?InvitationID=4269216"}], "updated": "2026-05-19T03:03:39.817766+09:00"}